{"DataForNerds":{"LastUpdatedUTC":"2021-08-04T00:27:08.8704077Z","SourceList":["https://docs.microsoft.com/en-us/windows/release-health/release-information","https://winreleaseinfoprod.blob.core.windows.net/winreleaseinfoprod/en-US.html"]},"Data":[{"Win10Version":"10.0.10240.16683","Version":"10240.16683","ReleaseDate":"2016-02-09","Article":"KB3135174","Comment":""},{"Win10Version":"10.0.10586.104","Version":"10586.104","ReleaseDate":"2016-02-09","Article":"KB3135173","Comment":""},{"Win10Version":"10.0.10586.122","Version":"10586.122","ReleaseDate":"2016-03-01","Article":"KB3140743","Comment":""},{"Win10Version":"10.0.10240.16725","Version":"10240.16725","ReleaseDate":"2016-03-08","Article":"KB3140745","Comment":""},{"Win10Version":"10.0.10586.164","Version":"10586.164","ReleaseDate":"2016-03-08","Article":"KB3140768","Comment":""},{"Win10Version":"10.0.10240.16769","Version":"10240.16769","ReleaseDate":"2016-04-12","Article":"KB3147461","Comment":""},{"Win10Version":"10.0.10586.218","Version":"10586.218","ReleaseDate":"2016-04-12","Article":"KB3147458","Comment":""},{"Win10Version":"10.0.10240.16854","Version":"10240.16854","ReleaseDate":"2016-05-10","Article":"KB3156387","Comment":""},{"Win10Version":"10.0.10586.318","Version":"10586.318","ReleaseDate":"2016-05-10","Article":"KB3156421","Comment":""},{"Win10Version":"10.0.10240.16942","Version":"10240.16942","ReleaseDate":"2016-06-14","Article":"KB3163017","Comment":""},{"Win10Version":"10.0.10586.420","Version":"10586.420","ReleaseDate":"2016-06-14","Article":"KB3163018","Comment":""},{"Win10Version":"10.0.10240.17024","Version":"10240.17024","ReleaseDate":"2016-07-12","Article":"KB3163912","Comment":""},{"Win10Version":"10.0.10586.494","Version":"10586.494","ReleaseDate":"2016-07-12","Article":"KB3172985","Comment":""},{"Win10Version":"10.0.14393.10","Version":"14393.10","ReleaseDate":"2016-08-02","Article":"KB3176929","Comment":""},{"Win10Version":"10.0.10240.17071","Version":"10240.17071","ReleaseDate":"2016-08-09","Article":"KB3176492","Comment":""},{"Win10Version":"10.0.10586.545","Version":"10586.545","ReleaseDate":"2016-08-09","Article":"KB3176493","Comment":""},{"Win10Version":"10.0.14393.51","Version":"14393.51","ReleaseDate":"2016-08-09","Article":"KB3176495","Comment":""},{"Win10Version":"10.0.14393.82","Version":"14393.82","ReleaseDate":"2016-08-23","Article":"KB3176934","Comment":""},{"Win10Version":"10.0.14393.105","Version":"14393.105","ReleaseDate":"2016-08-31","Article":"KB3176938","Comment":""},{"Win10Version":"10.0.10240.17113","Version":"10240.17113","ReleaseDate":"2016-09-13","Article":"KB3185611","Comment":""},{"Win10Version":"10.0.10586.589","Version":"10586.589","ReleaseDate":"2016-09-13","Article":"KB3185614","Comment":""},{"Win10Version":"10.0.14393.187","Version":"14393.187","ReleaseDate":"2016-09-13","Article":"KB3189866","Comment":""},{"Win10Version":"10.0.14393.189","Version":"14393.189","ReleaseDate":"2016-09-13","Article":"KB3189866","Comment":""},{"Win10Version":"10.0.10240.17113","Version":"10240.17113","ReleaseDate":"2016-09-20","Article":"KB3193821","Comment":""},{"Win10Version":"10.0.14393.187","Version":"14393.187","ReleaseDate":"2016-09-20","Article":"KB3193494","Comment":""},{"Win10Version":"10.0.14393.189","Version":"14393.189","ReleaseDate":"2016-09-20","Article":"KB3193494","Comment":""},{"Win10Version":"10.0.14393.222","Version":"14393.222","ReleaseDate":"2016-09-29","Article":"KB3194496","Comment":""},{"Win10Version":"10.0.10240.17146","Version":"10240.17146","ReleaseDate":"2016-10-11","Article":"KB3192440","Comment":""},{"Win10Version":"10.0.10586.633","Version":"10586.633","ReleaseDate":"2016-10-11","Article":"KB3192441","Comment":""},{"Win10Version":"10.0.14393.321","Version":"14393.321","ReleaseDate":"2016-10-11","Article":"KB3194798","Comment":""},{"Win10Version":"10.0.14393.351","Version":"14393.351","ReleaseDate":"2016-10-27","Article":"KB3197954","Comment":""},{"Win10Version":"10.0.10240.17190","Version":"10240.17190","ReleaseDate":"2016-11-08","Article":"KB3198585","Comment":""},{"Win10Version":"10.0.10586.679","Version":"10586.679","ReleaseDate":"2016-11-08","Article":"KB3198586","Comment":""},{"Win10Version":"10.0.14393.447","Version":"14393.447","ReleaseDate":"2016-11-08","Article":"KB3200970","Comment":""},{"Win10Version":"10.0.14393.448","Version":"14393.448","ReleaseDate":"2016-11-09","Article":"KB3200970","Comment":""},{"Win10Version":"10.0.10586.682","Version":"10586.682","ReleaseDate":"2016-11-14","Article":"KB3198586","Comment":""},{"Win10Version":"10.0.14393.479","Version":"14393.479","ReleaseDate":"2016-12-09","Article":"KB3201845","Comment":""},{"Win10Version":"10.0.10240.17202","Version":"10240.17202","ReleaseDate":"2016-12-13","Article":"KB3205383","Comment":""},{"Win10Version":"10.0.10586.713","Version":"10586.713","ReleaseDate":"2016-12-13","Article":"KB3205386","Comment":""},{"Win10Version":"10.0.14393.571","Version":"14393.571","ReleaseDate":"2016-12-13","Article":"KB3206632","Comment":""},{"Win10Version":"10.0.10240.17236","Version":"10240.17236","ReleaseDate":"2017-01-10","Article":"KB3210720","Comment":""},{"Win10Version":"10.0.10586.753","Version":"10586.753","ReleaseDate":"2017-01-10","Article":"KB3210721","Comment":""},{"Win10Version":"10.0.14393.693","Version":"14393.693","ReleaseDate":"2017-01-10","Article":"KB3213986","Comment":""},{"Win10Version":"10.0.14393.726","Version":"14393.726","ReleaseDate":"2017-01-26","Article":"KB 3216755","Comment":""},{"Win10Version":"10.0.14393.729","Version":"14393.729","ReleaseDate":"2017-01-30","Article":"KB4010672","Comment":""},{"Win10Version":"10.0.10240.17319","Version":"10240.17319","ReleaseDate":"2017-03-14","Article":"KB4012606","Comment":""},{"Win10Version":"10.0.10586.839","Version":"10586.839","ReleaseDate":"2017-03-14","Article":"KB4013198","Comment":""},{"Win10Version":"10.0.14393.953","Version":"14393.953","ReleaseDate":"2017-03-14","Article":"KB4013429","Comment":""},{"Win10Version":"10.0.14393.969","Version":"14393.969","ReleaseDate":"2017-03-20","Article":"KB4015438","Comment":""},{"Win10Version":"10.0.10240.17320","Version":"10240.17320","ReleaseDate":"2017-03-22","Article":"KB4016637","Comment":""},{"Win10Version":"10.0.10586.842","Version":"10586.842","ReleaseDate":"2017-03-22","Article":"KB4016636","Comment":""},{"Win10Version":"10.0.14393.970","Version":"14393.970","ReleaseDate":"2017-03-22","Article":"KB4016635","Comment":""},{"Win10Version":"10.0.15063.13","Version":"15063.13","ReleaseDate":"2017-04-05","Article":"KB4016251","Comment":""},{"Win10Version":"10.0.10240.17354","Version":"10240.17354","ReleaseDate":"2017-04-11","Article":"KB4015221","Comment":""},{"Win10Version":"10.0.10586.873","Version":"10586.873","ReleaseDate":"2017-04-11","Article":"KB4015219","Comment":""},{"Win10Version":"10.0.14393.1066","Version":"14393.1066","ReleaseDate":"2017-04-11","Article":"KB4015217","Comment":""},{"Win10Version":"10.0.14393.1083","Version":"14393.1083","ReleaseDate":"2017-04-11","Article":"KB4015217","Comment":""},{"Win10Version":"10.0.15063.138","Version":"15063.138","ReleaseDate":"2017-04-11","Article":"KB4015583","Comment":""},{"Win10Version":"10.0.15063.250","Version":"15063.250","ReleaseDate":"2017-04-25","Article":"KB4016240","Comment":""},{"Win10Version":"10.0.10240.17394","Version":"10240.17394","ReleaseDate":"2017-05-09","Article":"KB4019474","Comment":""},{"Win10Version":"10.0.10586.916","Version":"10586.916","ReleaseDate":"2017-05-09","Article":"KB4019473","Comment":""},{"Win10Version":"10.0.14393.1198","Version":"14393.1198","ReleaseDate":"2017-05-09","Article":"KB4019472","Comment":""},{"Win10Version":"10.0.15063.296","Version":"15063.296","ReleaseDate":"2017-05-09","Article":"KB4016871","Comment":""},{"Win10Version":"10.0.15063.297","Version":"15063.297","ReleaseDate":"2017-05-09","Article":"KB4016871","Comment":""},{"Win10Version":"10.0.15063.332","Version":"15063.332","ReleaseDate":"2017-05-25","Article":"KB4020102","Comment":""},{"Win10Version":"10.0.14393.1230","Version":"14393.1230","ReleaseDate":"2017-05-26","Article":"KB4023680","Comment":""},{"Win10Version":"10.0.10240.17443","Version":"10240.17443","ReleaseDate":"2017-06-13","Article":"KB4022727","Comment":""},{"Win10Version":"10.0.10586.962","Version":"10586.962","ReleaseDate":"2017-06-13","Article":"KB4022714","Comment":""},{"Win10Version":"10.0.14393.1358","Version":"14393.1358","ReleaseDate":"2017-06-13","Article":"KB4022715","Comment":""},{"Win10Version":"10.0.15063.413","Version":"15063.413","ReleaseDate":"2017-06-13","Article":"KB4022725","Comment":""},{"Win10Version":"10.0.15063.414","Version":"15063.414","ReleaseDate":"2017-06-13","Article":"KB4022725","Comment":""},{"Win10Version":"10.0.10240.17446","Version":"10240.17446","ReleaseDate":"2017-06-27","Article":"KB4032695","Comment":""},{"Win10Version":"10.0.10586.965","Version":"10586.965","ReleaseDate":"2017-06-27","Article":"KB4032693","Comment":""},{"Win10Version":"10.0.14393.1378","Version":"14393.1378","ReleaseDate":"2017-06-27","Article":"KB4022723","Comment":""},{"Win10Version":"10.0.15063.447","Version":"15063.447","ReleaseDate":"2017-06-27","Article":"KB4022716","Comment":""},{"Win10Version":"10.0.10240.17488","Version":"10240.17488","ReleaseDate":"2017-07-11","Article":"KB4025338","Comment":""},{"Win10Version":"10.0.10586.1007","Version":"10586.1007","ReleaseDate":"2017-07-11","Article":"KB4025344","Comment":""},{"Win10Version":"10.0.14393.1480","Version":"14393.1480","ReleaseDate":"2017-07-11","Article":"KB4025339","Comment":""},{"Win10Version":"10.0.15063.483","Version":"15063.483","ReleaseDate":"2017-07-11","Article":"KB4025342","Comment":""},{"Win10Version":"10.0.14393.1532","Version":"14393.1532","ReleaseDate":"2017-07-18","Article":"KB4025334 ","Comment":""},{"Win10Version":"10.0.15063.502","Version":"15063.502","ReleaseDate":"2017-07-31","Article":"KB4032188","Comment":""},{"Win10Version":"10.0.14393.1537","Version":"14393.1537","ReleaseDate":"2017-08-07","Article":"KB4038220","Comment":""},{"Win10Version":"10.0.10240.17533","Version":"10240.17533","ReleaseDate":"2017-08-08","Article":"KB4034668","Comment":""},{"Win10Version":"10.0.10586.1045","Version":"10586.1045","ReleaseDate":"2017-08-08","Article":"KB4034660","Comment":""},{"Win10Version":"10.0.14393.1593","Version":"14393.1593","ReleaseDate":"2017-08-08","Article":"KB4034658","Comment":""},{"Win10Version":"10.0.15063.540","Version":"15063.540","ReleaseDate":"2017-08-08","Article":"KB4034674","Comment":""},{"Win10Version":"10.0.14393.1613","Version":"14393.1613","ReleaseDate":"2017-08-16","Article":"KB4034661","Comment":""},{"Win10Version":"10.0.14393.1670","Version":"14393.1670","ReleaseDate":"2017-08-28","Article":"KB4039396","Comment":""},{"Win10Version":"10.0.10240.17609","Version":"10240.17609","ReleaseDate":"2017-09-12","Article":"KB4038781","Comment":""},{"Win10Version":"10.0.10586.1106","Version":"10586.1106","ReleaseDate":"2017-09-12","Article":"KB4038783","Comment":""},{"Win10Version":"10.0.14393.1715","Version":"14393.1715","ReleaseDate":"2017-09-12","Article":"KB4038782","Comment":""},{"Win10Version":"10.0.15063.608","Version":"15063.608","ReleaseDate":"2017-09-12","Article":"KB4038788","Comment":""},{"Win10Version":"10.0.15063.632","Version":"15063.632","ReleaseDate":"2017-09-25","Article":"KB4040724","Comment":""},{"Win10Version":"10.0.14393.1737","Version":"14393.1737","ReleaseDate":"2017-09-28","Article":"KB4038801","Comment":""},{"Win10Version":"10.0.10240.17643","Version":"10240.17643","ReleaseDate":"2017-10-10","Article":"KB4042895","Comment":""},{"Win10Version":"10.0.10586.1176","Version":"10586.1176","ReleaseDate":"2017-10-10","Article":"KB4041689","Comment":""},{"Win10Version":"10.0.14393.1770","Version":"14393.1770","ReleaseDate":"2017-10-10","Article":"KB4041691","Comment":""},{"Win10Version":"10.0.15063.674","Version":"15063.674","ReleaseDate":"2017-10-10","Article":"KB4041676","Comment":""},{"Win10Version":"10.0.14393.1794","Version":"14393.1794","ReleaseDate":"2017-10-17","Article":"KB4041688","Comment":""},{"Win10Version":"10.0.16299.19","Version":"16299.19","ReleaseDate":"2017-10-17","Article":"KB4043961","Comment":""},{"Win10Version":"10.0.10586.1177","Version":"10586.1177","ReleaseDate":"2017-11-02","Article":"KB4052232","Comment":""},{"Win10Version":"10.0.14393.1797","Version":"14393.1797","ReleaseDate":"2017-11-02","Article":"KB4052231","Comment":""},{"Win10Version":"10.0.15063.675","Version":"15063.675","ReleaseDate":"2017-11-02","Article":"KB4049370","Comment":""},{"Win10Version":"10.0.10240.17673","Version":"10240.17673","ReleaseDate":"2017-11-14","Article":"KB4048956","Comment":""},{"Win10Version":"10.0.10586.1232","Version":"10586.1232","ReleaseDate":"2017-11-14","Article":"KB4048952","Comment":""},{"Win10Version":"10.0.14393.1884","Version":"14393.1884","ReleaseDate":"2017-11-14","Article":"KB4048953","Comment":""},{"Win10Version":"10.0.15063.726","Version":"15063.726","ReleaseDate":"2017-11-14","Article":"KB4048954","Comment":""},{"Win10Version":"10.0.15063.728","Version":"15063.728","ReleaseDate":"2017-11-14","Article":"KB4048954","Comment":""},{"Win10Version":"10.0.15254.12","Version":"15254.12","ReleaseDate":"2017-11-14","Article":"KB4052314","Comment":""},{"Win10Version":"10.0.16299.64","Version":"16299.64","ReleaseDate":"2017-11-14","Article":"KB4048955","Comment":""},{"Win10Version":"10.0.15063.729","Version":"15063.729","ReleaseDate":"2017-11-22","Article":"KB4055254","Comment":""},{"Win10Version":"10.0.14393.1914","Version":"14393.1914","ReleaseDate":"2017-11-27","Article":"KB4051033","Comment":""},{"Win10Version":"10.0.16299.98","Version":"16299.98","ReleaseDate":"2017-11-30","Article":"KB4051963","Comment":""},{"Win10Version":"10.0.10240.17709","Version":"10240.17709","ReleaseDate":"2017-12-12","Article":"KB4053581","Comment":""},{"Win10Version":"10.0.10586.1295","Version":"10586.1295","ReleaseDate":"2017-12-12","Article":"KB4053578","Comment":""},{"Win10Version":"10.0.14393.1944","Version":"14393.1944","ReleaseDate":"2017-12-12","Article":"KB4053579","Comment":""},{"Win10Version":"10.0.15063.786","Version":"15063.786","ReleaseDate":"2017-12-12","Article":"KB4053580","Comment":""},{"Win10Version":"10.0.15254.124","Version":"15254.124","ReleaseDate":"2017-12-12","Article":"KB4056342 Update for Windows 10 Mobile","Comment":""},{"Win10Version":"10.0.16299.125","Version":"16299.125","ReleaseDate":"2017-12-12","Article":"KB4054517","Comment":""},{"Win10Version":"10.0.10240.17738","Version":"10240.17738","ReleaseDate":"2018-01-03","Article":"KB4056893","Comment":""},{"Win10Version":"10.0.10586.1356","Version":"10586.1356","ReleaseDate":"2018-01-03","Article":"KB4056888","Comment":""},{"Win10Version":"10.0.14393.2007","Version":"14393.2007","ReleaseDate":"2018-01-03","Article":"KB4056890","Comment":""},{"Win10Version":"10.0.15063.850","Version":"15063.850","ReleaseDate":"2018-01-03","Article":"KB4056891","Comment":""},{"Win10Version":"10.0.16299.192","Version":"16299.192","ReleaseDate":"2018-01-03","Article":"KB4056892","Comment":""},{"Win10Version":"10.0.15254.158","Version":"15254.158","ReleaseDate":"2018-01-05","Article":"KB4073117","Comment":""},{"Win10Version":"10.0.14393.2034","Version":"14393.2034","ReleaseDate":"2018-01-17","Article":"KB4057142","Comment":""},{"Win10Version":"10.0.15063.877","Version":"15063.877","ReleaseDate":"2018-01-17","Article":"KB4057144","Comment":""},{"Win10Version":"10.0.10240.17741","Version":"10240.17741","ReleaseDate":"2018-01-18","Article":"KB4075199","Comment":""},{"Win10Version":"10.0.10586.1358","Version":"10586.1358","ReleaseDate":"2018-01-18","Article":"KB4075200","Comment":""},{"Win10Version":"10.0.16299.201","Version":"16299.201","ReleaseDate":"2018-01-18","Article":"KB4073291","Comment":""},{"Win10Version":"10.0.10240.17741","Version":"10240.17741","ReleaseDate":"2018-01-31","Article":"KB4077735","Comment":""},{"Win10Version":"10.0.16299.214","Version":"16299.214","ReleaseDate":"2018-01-31","Article":"KB4058258","Comment":""},{"Win10Version":"10.0.10240.17770","Version":"10240.17770","ReleaseDate":"2018-02-13","Article":"KB4074596","Comment":""},{"Win10Version":"10.0.10586.1417","Version":"10586.1417","ReleaseDate":"2018-02-13","Article":"KB4074591","Comment":""},{"Win10Version":"10.0.14393.2068","Version":"14393.2068","ReleaseDate":"2018-02-13","Article":"KB4074590","Comment":""},{"Win10Version":"10.0.15063.909","Version":"15063.909","ReleaseDate":"2018-02-13","Article":"KB4074592","Comment":""},{"Win10Version":"10.0.16299.248","Version":"16299.248","ReleaseDate":"2018-02-13","Article":"KB4074588","Comment":""},{"Win10Version":"10.0.15254.248","Version":"15254.248","ReleaseDate":"2018-02-14","Article":"KB4077675","Comment":""},{"Win10Version":"10.0.14393.2097","Version":"14393.2097","ReleaseDate":"2018-02-22","Article":"KB4077525","Comment":""},{"Win10Version":"10.0.15063.936","Version":"15063.936","ReleaseDate":"2018-02-22","Article":"KB4077528","Comment":""},{"Win10Version":"10.0.16299.251","Version":"16299.251","ReleaseDate":"2018-03-05","Article":"KB4090913","Comment":""},{"Win10Version":"10.0.15063.936","Version":"15063.936","ReleaseDate":"2018-03-08","Article":"KB4092077","Comment":""},{"Win10Version":"10.0.10240.17797","Version":"10240.17797","ReleaseDate":"2018-03-13","Article":"KB4088786","Comment":""},{"Win10Version":"10.0.10586.1478","Version":"10586.1478","ReleaseDate":"2018-03-13","Article":"KB4088779","Comment":""},{"Win10Version":"10.0.14393.2125","Version":"14393.2125","ReleaseDate":"2018-03-13","Article":"KB4088787","Comment":""},{"Win10Version":"10.0.14393.2126","Version":"14393.2126","ReleaseDate":"2018-03-13","Article":"KB4088787","Comment":""},{"Win10Version":"10.0.15063.966","Version":"15063.966","ReleaseDate":"2018-03-13","Article":"KB4088782","Comment":""},{"Win10Version":"10.0.15063.968","Version":"15063.968","ReleaseDate":"2018-03-13","Article":"KB4088782","Comment":""},{"Win10Version":"10.0.16299.309","Version":"16299.309","ReleaseDate":"2018-03-13","Article":"KB4088776","Comment":""},{"Win10Version":"10.0.15254.313","Version":"15254.313","ReleaseDate":"2018-03-15","Article":"KB4090912 Update for Windows 10 Mobile","Comment":""},{"Win10Version":"10.0.14393.2155","Version":"14393.2155","ReleaseDate":"2018-03-22","Article":"KB4088889","Comment":""},{"Win10Version":"10.0.15063.994","Version":"15063.994","ReleaseDate":"2018-03-22","Article":"KB4088891","Comment":""},{"Win10Version":"10.0.16299.334","Version":"16299.334","ReleaseDate":"2018-03-22","Article":"KB4089848","Comment":""},{"Win10Version":"10.0.14393.2156","Version":"14393.2156","ReleaseDate":"2018-03-29","Article":"KB4096309","Comment":""},{"Win10Version":"10.0.10240.17831","Version":"10240.17831","ReleaseDate":"2018-04-10","Article":"KB4093111","Comment":""},{"Win10Version":"10.0.10586.1540","Version":"10586.1540","ReleaseDate":"2018-04-10","Article":"KB4093109","Comment":""},{"Win10Version":"10.0.14393.2189","Version":"14393.2189","ReleaseDate":"2018-04-10","Article":"KB4093119","Comment":""},{"Win10Version":"10.0.15063.1029","Version":"15063.1029","ReleaseDate":"2018-04-10","Article":"KB4093107","Comment":""},{"Win10Version":"10.0.15254.369","Version":"15254.369","ReleaseDate":"2018-04-10","Article":"KB4099572 Update for Windows 10 Mobile","Comment":""},{"Win10Version":"10.0.16299.371","Version":"16299.371","ReleaseDate":"2018-04-10","Article":"KB4093112","Comment":""},{"Win10Version":"10.0.14393.2214","Version":"14393.2214","ReleaseDate":"2018-04-17","Article":"KB4093120","Comment":""},{"Win10Version":"10.0.15063.1058","Version":"15063.1058","ReleaseDate":"2018-04-17","Article":"KB4093117","Comment":""},{"Win10Version":"10.0.16299.402","Version":"16299.402","ReleaseDate":"2018-04-23","Article":"KB4093105","Comment":""},{"Win10Version":"10.0.10240.17861","Version":"10240.17861","ReleaseDate":"2018-05-08","Article":"KB4103716","Comment":""},{"Win10Version":"10.0.14393.2248","Version":"14393.2248","ReleaseDate":"2018-05-08","Article":"KB4103723","Comment":""},{"Win10Version":"10.0.15063.1088","Version":"15063.1088","ReleaseDate":"2018-05-08","Article":"KB4103731","Comment":""},{"Win10Version":"10.0.15254.401","Version":"15254.401","ReleaseDate":"2018-05-08","Article":"KB4134196 Update for Windows 10 Mobile","Comment":""},{"Win10Version":"10.0.16299.431","Version":"16299.431","ReleaseDate":"2018-05-08","Article":"KB4103727","Comment":""},{"Win10Version":"10.0.17134.48","Version":"17134.48","ReleaseDate":"2018-05-08","Article":"KB4103721","Comment":""},{"Win10Version":"10.0.14393.2273","Version":"14393.2273","ReleaseDate":"2018-05-17","Article":"KB4103720","Comment":""},{"Win10Version":"10.0.15063.1112","Version":"15063.1112","ReleaseDate":"2018-05-17","Article":"KB4103722","Comment":""},{"Win10Version":"10.0.16299.461","Version":"16299.461","ReleaseDate":"2018-05-21","Article":"KB4103714","Comment":""},{"Win10Version":"10.0.17134.81","Version":"17134.81","ReleaseDate":"2018-05-23","Article":"KB4100403","Comment":""},{"Win10Version":"10.0.17134.83","Version":"17134.83","ReleaseDate":"2018-06-05","Article":"KB4338548","Comment":""},{"Win10Version":"10.0.10240.17889","Version":"10240.17889","ReleaseDate":"2018-06-12","Article":"KB4284860","Comment":""},{"Win10Version":"10.0.14393.2312","Version":"14393.2312","ReleaseDate":"2018-06-12","Article":"KB4284880","Comment":""},{"Win10Version":"10.0.15063.1155","Version":"15063.1155","ReleaseDate":"2018-06-12","Article":"KB4284874","Comment":""},{"Win10Version":"10.0.15254.489","Version":"15254.489","ReleaseDate":"2018-06-12","Article":"KB4316692 Update for Windows 10 Mobile","Comment":""},{"Win10Version":"10.0.16299.492","Version":"16299.492","ReleaseDate":"2018-06-12","Article":"KB4284819","Comment":""},{"Win10Version":"10.0.17134.112","Version":"17134.112","ReleaseDate":"2018-06-12","Article":"KB4284835","Comment":""},{"Win10Version":"10.0.14393.2339","Version":"14393.2339","ReleaseDate":"2018-06-21","Article":"KB4284833","Comment":""},{"Win10Version":"10.0.15063.1182","Version":"15063.1182","ReleaseDate":"2018-06-21","Article":"KB4284830","Comment":""},{"Win10Version":"10.0.16299.522","Version":"16299.522","ReleaseDate":"2018-06-21","Article":"KB4284822","Comment":""},{"Win10Version":"10.0.17134.137","Version":"17134.137","ReleaseDate":"2018-06-26","Article":"KB4284848","Comment":""},{"Win10Version":"10.0.10240.17914","Version":"10240.17914","ReleaseDate":"2018-07-10","Article":"KB4338829","Comment":""},{"Win10Version":"10.0.14393.2363","Version":"14393.2363","ReleaseDate":"2018-07-10","Article":"KB4338814","Comment":""},{"Win10Version":"10.0.15063.1206","Version":"15063.1206","ReleaseDate":"2018-07-10","Article":"KB4338826","Comment":""},{"Win10Version":"10.0.16299.547","Version":"16299.547","ReleaseDate":"2018-07-10","Article":"KB4338825","Comment":""},{"Win10Version":"10.0.17134.165","Version":"17134.165","ReleaseDate":"2018-07-10","Article":"KB4338819","Comment":""},{"Win10Version":"10.0.10240.17918","Version":"10240.17918","ReleaseDate":"2018-07-16","Article":"KB4345455","Comment":""},{"Win10Version":"10.0.14393.2368","Version":"14393.2368","ReleaseDate":"2018-07-16","Article":"KB4345418","Comment":""},{"Win10Version":"10.0.15063.1209","Version":"15063.1209","ReleaseDate":"2018-07-16","Article":"KB4345419","Comment":""},{"Win10Version":"10.0.16299.551","Version":"16299.551","ReleaseDate":"2018-07-16","Article":"KB4345420","Comment":""},{"Win10Version":"10.0.17134.167","Version":"17134.167","ReleaseDate":"2018-07-16","Article":"KB4345421","Comment":""},{"Win10Version":"10.0.14393.2395","Version":"14393.2395","ReleaseDate":"2018-07-24","Article":"KB4338822","Comment":""},{"Win10Version":"10.0.15063.1235","Version":"15063.1235","ReleaseDate":"2018-07-24","Article":"KB4338827","Comment":""},{"Win10Version":"10.0.16299.579","Version":"16299.579","ReleaseDate":"2018-07-24","Article":"KB4338817","Comment":""},{"Win10Version":"10.0.17134.191","Version":"17134.191","ReleaseDate":"2018-07-24","Article":"KB4340917","Comment":""},{"Win10Version":"10.0.14393.2396","Version":"14393.2396","ReleaseDate":"2018-07-30","Article":"KB4346877","Comment":""},{"Win10Version":"10.0.10240.17946","Version":"10240.17946","ReleaseDate":"2018-08-14","Article":"KB4343892","Comment":""},{"Win10Version":"10.0.14393.2430","Version":"14393.2430","ReleaseDate":"2018-08-14","Article":"KB4343887","Comment":""},{"Win10Version":"10.0.15063.1266","Version":"15063.1266","ReleaseDate":"2018-08-14","Article":"KB4343885","Comment":""},{"Win10Version":"10.0.15254.527","Version":"15254.527","ReleaseDate":"2018-08-14","Article":"KB4346644 Update for Windows 10 Mobile","Comment":""},{"Win10Version":"10.0.16299.611","Version":"16299.611","ReleaseDate":"2018-08-14","Article":"KB4343897","Comment":""},{"Win10Version":"10.0.17134.228","Version":"17134.228","ReleaseDate":"2018-08-14","Article":"KB4343909","Comment":""},{"Win10Version":"10.0.14393.2457","Version":"14393.2457","ReleaseDate":"2018-08-30","Article":"KB4343884","Comment":""},{"Win10Version":"10.0.15063.1292","Version":"15063.1292","ReleaseDate":"2018-08-30","Article":"KB4343889","Comment":""},{"Win10Version":"10.0.16299.637","Version":"16299.637","ReleaseDate":"2018-08-30","Article":"KB4343893","Comment":""},{"Win10Version":"10.0.17134.254","Version":"17134.254","ReleaseDate":"2018-08-30","Article":"KB4346783","Comment":""},{"Win10Version":"10.0.10240.17976","Version":"10240.17976","ReleaseDate":"2018-09-11","Article":"KB4457132","Comment":""},{"Win10Version":"10.0.14393.2485","Version":"14393.2485","ReleaseDate":"2018-09-11","Article":"KB4457131","Comment":""},{"Win10Version":"10.0.15063.1324","Version":"15063.1324","ReleaseDate":"2018-09-11","Article":"KB4457138","Comment":""},{"Win10Version":"10.0.15254.530","Version":"15254.530","ReleaseDate":"2018-09-11","Article":"KB4459082 Update for Windows 10 Mobile","Comment":""},{"Win10Version":"10.0.16299.665","Version":"16299.665","ReleaseDate":"2018-09-11","Article":"KB4457142","Comment":""},{"Win10Version":"10.0.17134.285","Version":"17134.285","ReleaseDate":"2018-09-11","Article":"KB4457128","Comment":""},{"Win10Version":"10.0.16299.666","Version":"16299.666","ReleaseDate":"2018-09-17","Article":"KB4464217","Comment":""},{"Win10Version":"10.0.17134.286","Version":"17134.286","ReleaseDate":"2018-09-17","Article":"KB4464218","Comment":""},{"Win10Version":"10.0.14393.2515","Version":"14393.2515","ReleaseDate":"2018-09-20","Article":"KB4457127","Comment":""},{"Win10Version":"10.0.15063.1358","Version":"15063.1358","ReleaseDate":"2018-09-20","Article":"KB4457141","Comment":""},{"Win10Version":"10.0.16299.699","Version":"16299.699","ReleaseDate":"2018-09-26","Article":"KB4457136","Comment":""},{"Win10Version":"10.0.17134.320","Version":"17134.320","ReleaseDate":"2018-09-26","Article":"KB4458469","Comment":""},{"Win10Version":"10.0.10240.18005","Version":"10240.18005","ReleaseDate":"2018-10-09","Article":"KB4462922","Comment":""},{"Win10Version":"10.0.14393.2551","Version":"14393.2551","ReleaseDate":"2018-10-09","Article":"KB4462917","Comment":""},{"Win10Version":"10.0.15063.1387","Version":"15063.1387","ReleaseDate":"2018-10-09","Article":"KB4462937","Comment":""},{"Win10Version":"10.0.15254.538","Version":"15254.538","ReleaseDate":"2018-10-09","Article":"KB4464853 Update for Windows 10 Mobile","Comment":""},{"Win10Version":"10.0.16299.726","Version":"16299.726","ReleaseDate":"2018-10-09","Article":"KB4462918","Comment":""},{"Win10Version":"10.0.17134.345","Version":"17134.345","ReleaseDate":"2018-10-09","Article":"KB4462919","Comment":""},{"Win10Version":"10.0.17763.55","Version":"17763.55","ReleaseDate":"2018-10-09","Article":"KB4464330","Comment":""},{"Win10Version":"10.0.14393.2580","Version":"14393.2580","ReleaseDate":"2018-10-18","Article":"KB4462928","Comment":""},{"Win10Version":"10.0.15063.1418","Version":"15063.1418","ReleaseDate":"2018-10-18","Article":"KB4462939","Comment":""},{"Win10Version":"10.0.16299.755","Version":"16299.755","ReleaseDate":"2018-10-18","Article":"KB4462932","Comment":""},{"Win10Version":"10.0.17134.376","Version":"17134.376","ReleaseDate":"2018-10-24","Article":"KB4462933","Comment":""},{"Win10Version":"10.0.10240.18036","Version":"10240.18036","ReleaseDate":"2018-11-13","Article":"KB4467680","Comment":""},{"Win10Version":"10.0.14393.2608","Version":"14393.2608","ReleaseDate":"2018-11-13","Article":"KB4467691","Comment":""},{"Win10Version":"10.0.15063.1446","Version":"15063.1446","ReleaseDate":"2018-11-13","Article":"KB4467696","Comment":""},{"Win10Version":"10.0.15254.541","Version":"15254.541","ReleaseDate":"2018-11-13","Article":"KB4469220 Update for Windows 10 Mobile","Comment":""},{"Win10Version":"10.0.16299.785","Version":"16299.785","ReleaseDate":"2018-11-13","Article":"KB4467686","Comment":""},{"Win10Version":"10.0.17134.407","Version":"17134.407","ReleaseDate":"2018-11-13","Article":"KB4467702","Comment":""},{"Win10Version":"10.0.17763.107","Version":"17763.107","ReleaseDate":"2018-11-13","Article":"KB4464455","Comment":""},{"Win10Version":"10.0.17763.134","Version":"17763.134","ReleaseDate":"2018-11-13","Article":"KB4467708","Comment":""},{"Win10Version":"10.0.14393.2639","Version":"14393.2639","ReleaseDate":"2018-11-27","Article":"KB4467684","Comment":""},{"Win10Version":"10.0.15063.1478","Version":"15063.1478","ReleaseDate":"2018-11-27","Article":"KB4467699","Comment":""},{"Win10Version":"10.0.16299.820","Version":"16299.820","ReleaseDate":"2018-11-27","Article":"KB4467681","Comment":""},{"Win10Version":"10.0.17134.441","Version":"17134.441","ReleaseDate":"2018-11-27","Article":"KB4467682","Comment":""},{"Win10Version":"10.0.14393.2641","Version":"14393.2641","ReleaseDate":"2018-12-03","Article":"KB4478877","Comment":""},{"Win10Version":"10.0.17763.168","Version":"17763.168","ReleaseDate":"2018-12-05","Article":"KB4469342","Comment":""},{"Win10Version":"10.0.10240.18063","Version":"10240.18063","ReleaseDate":"2018-12-11","Article":"KB4471323","Comment":""},{"Win10Version":"10.0.14393.2665","Version":"14393.2665","ReleaseDate":"2018-12-11","Article":"KB4471321","Comment":""},{"Win10Version":"10.0.15063.1506","Version":"15063.1506","ReleaseDate":"2018-12-11","Article":"KB4471327","Comment":""},{"Win10Version":"10.0.15254.544","Version":"15254.544","ReleaseDate":"2018-12-11","Article":"KB4478936 Update for Windows 10 Mobile","Comment":""},{"Win10Version":"10.0.16299.846","Version":"16299.846","ReleaseDate":"2018-12-11","Article":"KB4471329","Comment":""},{"Win10Version":"10.0.17134.471","Version":"17134.471","ReleaseDate":"2018-12-11","Article":"KB4471324","Comment":""},{"Win10Version":"10.0.17763.194","Version":"17763.194","ReleaseDate":"2018-12-11","Article":"KB4471332","Comment":""},{"Win10Version":"10.0.10240.18064","Version":"10240.18064","ReleaseDate":"2018-12-19","Article":"KB4483228","Comment":""},{"Win10Version":"10.0.14393.2670","Version":"14393.2670","ReleaseDate":"2018-12-19","Article":"KB4483229","Comment":""},{"Win10Version":"10.0.15063.1508","Version":"15063.1508","ReleaseDate":"2018-12-19","Article":"KB4483230","Comment":""},{"Win10Version":"10.0.16299.847","Version":"16299.847","ReleaseDate":"2018-12-19","Article":"KB4483232","Comment":""},{"Win10Version":"10.0.17134.472","Version":"17134.472","ReleaseDate":"2018-12-19","Article":"KB4483234","Comment":""},{"Win10Version":"10.0.17763.195","Version":"17763.195","ReleaseDate":"2018-12-19","Article":"KB4483235","Comment":""},{"Win10Version":"10.0.10240.18094","Version":"10240.18094","ReleaseDate":"2019-01-08","Article":"KB4480962","Comment":""},{"Win10Version":"10.0.14393.2724","Version":"14393.2724","ReleaseDate":"2019-01-08","Article":"KB4480961","Comment":""},{"Win10Version":"10.0.15063.1563","Version":"15063.1563","ReleaseDate":"2019-01-08","Article":"KB4480973","Comment":""},{"Win10Version":"10.0.15254.547","Version":"15254.547","ReleaseDate":"2019-01-08","Article":"KB4483203 Update for Windows 10 Mobile","Comment":""},{"Win10Version":"10.0.16299.904","Version":"16299.904","ReleaseDate":"2019-01-08","Article":"KB4480978","Comment":""},{"Win10Version":"10.0.17134.523","Version":"17134.523","ReleaseDate":"2019-01-08","Article":"KB4480966","Comment":""},{"Win10Version":"10.0.17763.253","Version":"17763.253","ReleaseDate":"2019-01-08","Article":"KB4480116","Comment":""},{"Win10Version":"10.0.15063.1596","Version":"15063.1596","ReleaseDate":"2019-01-15","Article":"KB4480959","Comment":""},{"Win10Version":"10.0.16299.936","Version":"16299.936","ReleaseDate":"2019-01-15","Article":"KB4480967","Comment":""},{"Win10Version":"10.0.17134.556","Version":"17134.556","ReleaseDate":"2019-01-15","Article":"KB4480976","Comment":""},{"Win10Version":"10.0.14393.2759","Version":"14393.2759","ReleaseDate":"2019-01-17","Article":"KB4480977","Comment":""},{"Win10Version":"10.0.17763.292","Version":"17763.292","ReleaseDate":"2019-01-22","Article":"KB4476976","Comment":""},{"Win10Version":"10.0.10240.18132","Version":"10240.18132","ReleaseDate":"2019-02-12","Article":"KB4487018","Comment":""},{"Win10Version":"10.0.14393.2791","Version":"14393.2791","ReleaseDate":"2019-02-12","Article":"KB4487026","Comment":""},{"Win10Version":"10.0.15063.1631","Version":"15063.1631","ReleaseDate":"2019-02-12","Article":"KB4487020","Comment":""},{"Win10Version":"10.0.15254.552","Version":"15254.552","ReleaseDate":"2019-02-12","Article":"KB4487695 Update for Windows 10 Mobile","Comment":""},{"Win10Version":"10.0.16299.967","Version":"16299.967","ReleaseDate":"2019-02-12","Article":"KB4486996","Comment":""},{"Win10Version":"10.0.17134.590","Version":"17134.590","ReleaseDate":"2019-02-12","Article":"KB4487017","Comment":""},{"Win10Version":"10.0.17763.316","Version":"17763.316","ReleaseDate":"2019-02-12","Article":"KB4487044","Comment":""},{"Win10Version":"10.0.14393.2828","Version":"14393.2828","ReleaseDate":"2019-02-19","Article":"KB4487006","Comment":""},{"Win10Version":"10.0.15063.1659","Version":"15063.1659","ReleaseDate":"2019-02-19","Article":"KB4487011","Comment":""},{"Win10Version":"10.0.16299.1004","Version":"16299.1004","ReleaseDate":"2019-02-19","Article":"KB4487021","Comment":""},{"Win10Version":"10.0.17134.619","Version":"17134.619","ReleaseDate":"2019-02-19","Article":"KB4487029","Comment":""},{"Win10Version":"10.0.10240.18135","Version":"10240.18135","ReleaseDate":"2019-02-21","Article":"KB4491101","Comment":""},{"Win10Version":"10.0.17763.348","Version":"17763.348","ReleaseDate":"2019-03-01","Article":"KB4482887","Comment":""},{"Win10Version":"10.0.10240.18158","Version":"10240.18158","ReleaseDate":"2019-03-12","Article":"KB4489872","Comment":""},{"Win10Version":"10.0.14393.2848","Version":"14393.2848","ReleaseDate":"2019-03-12","Article":"KB4489882","Comment":""},{"Win10Version":"10.0.15063.1689","Version":"15063.1689","ReleaseDate":"2019-03-12","Article":"KB4489871","Comment":""},{"Win10Version":"10.0.15254.556","Version":"15254.556","ReleaseDate":"2019-03-12","Article":"KB4491736 Update for Windows 10 Mobile","Comment":""},{"Win10Version":"10.0.16299.1029","Version":"16299.1029","ReleaseDate":"2019-03-12","Article":"KB4489886","Comment":""},{"Win10Version":"10.0.17134.648","Version":"17134.648","ReleaseDate":"2019-03-12","Article":"KB4489868","Comment":""},{"Win10Version":"10.0.17763.379","Version":"17763.379","ReleaseDate":"2019-03-12","Article":"KB4489899","Comment":""},{"Win10Version":"10.0.14393.2879","Version":"14393.2879","ReleaseDate":"2019-03-19","Article":"KB4489889","Comment":""},{"Win10Version":"10.0.15063.1716","Version":"15063.1716","ReleaseDate":"2019-03-19","Article":"KB4489888","Comment":""},{"Win10Version":"10.0.16299.1059","Version":"16299.1059","ReleaseDate":"2019-03-19","Article":"KB4489890","Comment":""},{"Win10Version":"10.0.17134.677","Version":"17134.677","ReleaseDate":"2019-03-19","Article":"KB4489894","Comment":""},{"Win10Version":"10.0.17763.402","Version":"17763.402","ReleaseDate":"2019-03-26","Article":"KB4490481","Comment":""},{"Win10Version":"10.0.10240.18186","Version":"10240.18186","ReleaseDate":"2019-04-09","Article":"KB4493475","Comment":""},{"Win10Version":"10.0.14393.2906","Version":"14393.2906","ReleaseDate":"2019-04-09","Article":"KB4493470","Comment":""},{"Win10Version":"10.0.15063.1746","Version":"15063.1746","ReleaseDate":"2019-04-09","Article":"KB4493474","Comment":""},{"Win10Version":"10.0.15254.562","Version":"15254.562","ReleaseDate":"2019-04-09","Article":"KB4495357 Update for Windows 10 Mobile","Comment":""},{"Win10Version":"10.0.16299.1087","Version":"16299.1087","ReleaseDate":"2019-04-09","Article":"KB4493441","Comment":""},{"Win10Version":"10.0.17134.706","Version":"17134.706","ReleaseDate":"2019-04-09","Article":"KB4493464","Comment":""},{"Win10Version":"10.0.17763.437","Version":"17763.437","ReleaseDate":"2019-04-09","Article":"KB4493509","Comment":""},{"Win10Version":"10.0.10240.18187","Version":"10240.18187","ReleaseDate":"2019-04-25","Article":"KB4498375","Comment":""},{"Win10Version":"10.0.14393.2941","Version":"14393.2941","ReleaseDate":"2019-04-25","Article":"KB4493473","Comment":""},{"Win10Version":"10.0.15063.1784","Version":"15063.1784","ReleaseDate":"2019-04-25","Article":"KB4493436","Comment":""},{"Win10Version":"10.0.16299.1127","Version":"16299.1127","ReleaseDate":"2019-04-25","Article":"KB4493440","Comment":""},{"Win10Version":"10.0.17134.753","Version":"17134.753","ReleaseDate":"2019-04-25","Article":"KB4493437","Comment":""},{"Win10Version":"10.0.17763.439","Version":"17763.439","ReleaseDate":"2019-05-01","Article":"KB4501835","Comment":""},{"Win10Version":"10.0.15063.1785","Version":"15063.1785","ReleaseDate":"2019-05-02","Article":"KB4502112","Comment":""},{"Win10Version":"10.0.17763.475","Version":"17763.475","ReleaseDate":"2019-05-03","Article":"KB4495667","Comment":""},{"Win10Version":"10.0.10240.18215","Version":"10240.18215","ReleaseDate":"2019-05-14","Article":"KB4499154","Comment":""},{"Win10Version":"10.0.14393.2969","Version":"14393.2969","ReleaseDate":"2019-05-14","Article":"KB4494440","Comment":""},{"Win10Version":"10.0.15063.1805","Version":"15063.1805","ReleaseDate":"2019-05-14","Article":"KB4499181","Comment":""},{"Win10Version":"10.0.15254.566","Version":"15254.566","ReleaseDate":"2019-05-14","Article":"KB4500154 Update for Windows 10 Mobile","Comment":""},{"Win10Version":"10.0.16299.1146","Version":"16299.1146","ReleaseDate":"2019-05-14","Article":"KB4499179","Comment":""},{"Win10Version":"10.0.17134.765","Version":"17134.765","ReleaseDate":"2019-05-14","Article":"KB4499167","Comment":""},{"Win10Version":"10.0.17763.503","Version":"17763.503","ReleaseDate":"2019-05-14","Article":"KB4494441","Comment":""},{"Win10Version":"10.0.10240.18218","Version":"10240.18218","ReleaseDate":"2019-05-19","Article":"KB4505051","Comment":""},{"Win10Version":"10.0.14393.2972","Version":"14393.2972","ReleaseDate":"2019-05-19","Article":"KB4505052","Comment":""},{"Win10Version":"10.0.15063.1808","Version":"15063.1808","ReleaseDate":"2019-05-19","Article":"KB4505055","Comment":""},{"Win10Version":"10.0.16299.1150","Version":"16299.1150","ReleaseDate":"2019-05-19","Article":"KB4505062","Comment":""},{"Win10Version":"10.0.17134.766","Version":"17134.766","ReleaseDate":"2019-05-19","Article":"KB4505064","Comment":""},{"Win10Version":"10.0.17763.504","Version":"17763.504","ReleaseDate":"2019-05-19","Article":"KB4505056","Comment":""},{"Win10Version":"10.0.17134.799","Version":"17134.799","ReleaseDate":"2019-05-21","Article":"KB4499183","Comment":""},{"Win10Version":"10.0.17763.529","Version":"17763.529","ReleaseDate":"2019-05-21","Article":"KB4497934","Comment":""},{"Win10Version":"10.0.14393.2999","Version":"14393.2999","ReleaseDate":"2019-05-23","Article":"KB4499177","Comment":""},{"Win10Version":"10.0.15063.1839","Version":"15063.1839","ReleaseDate":"2019-05-28","Article":"KB4499162","Comment":""},{"Win10Version":"10.0.16299.1182","Version":"16299.1182","ReleaseDate":"2019-05-28","Article":"KB4499147","Comment":""},{"Win10Version":"10.0.18362.145","Version":"18362.145","ReleaseDate":"2019-05-29","Article":"KB4497935","Comment":""},{"Win10Version":"10.0.10240.18244","Version":"10240.18244","ReleaseDate":"2019-06-11","Article":"KB4503291","Comment":""},{"Win10Version":"10.0.14393.3025","Version":"14393.3025","ReleaseDate":"2019-06-11","Article":"KB4503267","Comment":""},{"Win10Version":"10.0.15063.1868","Version":"15063.1868","ReleaseDate":"2019-06-11","Article":"KB4503279","Comment":""},{"Win10Version":"10.0.15254.572","Version":"15254.572","ReleaseDate":"2019-06-11","Article":"KB4505390 Update for Windows 10 Mobile","Comment":""},{"Win10Version":"10.0.16299.1217","Version":"16299.1217","ReleaseDate":"2019-06-11","Article":"KB4503284","Comment":""},{"Win10Version":"10.0.17134.829","Version":"17134.829","ReleaseDate":"2019-06-11","Article":"KB4503286","Comment":""},{"Win10Version":"10.0.17763.557","Version":"17763.557","ReleaseDate":"2019-06-11","Article":"KB4503327","Comment":""},{"Win10Version":"10.0.18362.175","Version":"18362.175","ReleaseDate":"2019-06-11","Article":"KB4503293","Comment":""},{"Win10Version":"10.0.14393.3053","Version":"14393.3053","ReleaseDate":"2019-06-18","Article":"KB4503294","Comment":""},{"Win10Version":"10.0.15063.1897","Version":"15063.1897","ReleaseDate":"2019-06-18","Article":"KB4503289","Comment":""},{"Win10Version":"10.0.16299.1237","Version":"16299.1237","ReleaseDate":"2019-06-18","Article":"KB4503281","Comment":""},{"Win10Version":"10.0.17134.858","Version":"17134.858","ReleaseDate":"2019-06-18","Article":"KB4503288","Comment":""},{"Win10Version":"10.0.17763.592","Version":"17763.592","ReleaseDate":"2019-06-18","Article":"KB4501371","Comment":""},{"Win10Version":"10.0.15063.1898","Version":"15063.1898","ReleaseDate":"2019-06-26","Article":"KB4509476","Comment":""},{"Win10Version":"10.0.16299.1239","Version":"16299.1239","ReleaseDate":"2019-06-26","Article":"KB4509477","Comment":""},{"Win10Version":"10.0.17134.860","Version":"17134.860","ReleaseDate":"2019-06-26","Article":"KB4509478","Comment":""},{"Win10Version":"10.0.17763.593","Version":"17763.593","ReleaseDate":"2019-06-26","Article":"KB4509479","Comment":""},{"Win10Version":"10.0.14393.3056","Version":"14393.3056","ReleaseDate":"2019-06-27","Article":"KB4509475","Comment":""},{"Win10Version":"10.0.18362.207","Version":"18362.207","ReleaseDate":"2019-06-27","Article":"KB4501375","Comment":""},{"Win10Version":"10.0.10240.18275","Version":"10240.18275","ReleaseDate":"2019-07-09","Article":"KB4507458","Comment":""},{"Win10Version":"10.0.14393.3085","Version":"14393.3085","ReleaseDate":"2019-07-09","Article":"KB4507460","Comment":""},{"Win10Version":"10.0.15063.1928","Version":"15063.1928","ReleaseDate":"2019-07-09","Article":"KB4507450","Comment":""},{"Win10Version":"10.0.15254.575","Version":"15254.575","ReleaseDate":"2019-07-09","Article":"KB4509104 Update for Windows 10 Mobile ","Comment":""},{"Win10Version":"10.0.16299.1268","Version":"16299.1268","ReleaseDate":"2019-07-09","Article":"KB4507455","Comment":""},{"Win10Version":"10.0.17134.885","Version":"17134.885","ReleaseDate":"2019-07-09","Article":"KB4507435","Comment":""},{"Win10Version":"10.0.17763.615","Version":"17763.615","ReleaseDate":"2019-07-09","Article":"KB4507469","Comment":""},{"Win10Version":"10.0.18362.239","Version":"18362.239","ReleaseDate":"2019-07-09","Article":"KB4507453","Comment":""},{"Win10Version":"10.0.14393.3115","Version":"14393.3115","ReleaseDate":"2019-07-16","Article":"KB4507459","Comment":""},{"Win10Version":"10.0.15063.1955","Version":"15063.1955","ReleaseDate":"2019-07-16","Article":"KB4507467","Comment":""},{"Win10Version":"10.0.16299.1296","Version":"16299.1296","ReleaseDate":"2019-07-16","Article":"KB4507465","Comment":""},{"Win10Version":"10.0.17134.915","Version":"17134.915","ReleaseDate":"2019-07-16","Article":"KB4507466","Comment":""},{"Win10Version":"10.0.17763.652","Version":"17763.652","ReleaseDate":"2019-07-22","Article":"KB4505658","Comment":""},{"Win10Version":"10.0.18362.267","Version":"18362.267","ReleaseDate":"2019-07-26","Article":"KB4505903","Comment":""},{"Win10Version":"10.0.10240.18305","Version":"10240.18305","ReleaseDate":"2019-08-13","Article":"KB4512497","Comment":""},{"Win10Version":"10.0.14393.3144","Version":"14393.3144","ReleaseDate":"2019-08-13","Article":"KB4512517","Comment":""},{"Win10Version":"10.0.15063.1988","Version":"15063.1988","ReleaseDate":"2019-08-13","Article":"KB4512507","Comment":""},{"Win10Version":"10.0.15254.582","Version":"15254.582","ReleaseDate":"2019-08-13","Article":"KB4513172 Update for Windows 10 Mobile","Comment":""},{"Win10Version":"10.0.16299.1331","Version":"16299.1331","ReleaseDate":"2019-08-13","Article":"KB4512516","Comment":""},{"Win10Version":"10.0.17134.950","Version":"17134.950","ReleaseDate":"2019-08-13","Article":"KB4512501","Comment":""},{"Win10Version":"10.0.17763.678","Version":"17763.678","ReleaseDate":"2019-08-13","Article":"KB4511553","Comment":""},{"Win10Version":"10.0.18362.295","Version":"18362.295","ReleaseDate":"2019-08-13","Article":"KB4512508","Comment":""},{"Win10Version":"10.0.16299.1365","Version":"16299.1365","ReleaseDate":"2019-08-16","Article":"KB4512494","Comment":""},{"Win10Version":"10.0.10240.18308","Version":"10240.18308","ReleaseDate":"2019-08-17","Article":"KB4517276","Comment":""},{"Win10Version":"10.0.14393.3181","Version":"14393.3181","ReleaseDate":"2019-08-17","Article":"KB4512495","Comment":""},{"Win10Version":"10.0.15063.2021","Version":"15063.2021","ReleaseDate":"2019-08-17","Article":"KB4512474","Comment":""},{"Win10Version":"10.0.17763.720","Version":"17763.720","ReleaseDate":"2019-08-17","Article":"KB4512534","Comment":""},{"Win10Version":"10.0.17134.984","Version":"17134.984","ReleaseDate":"2019-08-19","Article":"KB4512509","Comment":""},{"Win10Version":"10.0.18362.329","Version":"18362.329","ReleaseDate":"2019-08-30","Article":"KB4512941","Comment":""},{"Win10Version":"10.0.10240.18333","Version":"10240.18333","ReleaseDate":"2019-09-10","Article":"KB4516070","Comment":""},{"Win10Version":"10.0.14393.3204","Version":"14393.3204","ReleaseDate":"2019-09-10","Article":"KB4516044","Comment":""},{"Win10Version":"10.0.15063.2045","Version":"15063.2045","ReleaseDate":"2019-09-10","Article":"KB4516068","Comment":""},{"Win10Version":"10.0.15254.587","Version":"15254.587","ReleaseDate":"2019-09-10","Article":"KB4518514 Update for Windows 10 Mobile","Comment":""},{"Win10Version":"10.0.16299.1387","Version":"16299.1387","ReleaseDate":"2019-09-10","Article":"KB4516066","Comment":""},{"Win10Version":"10.0.17134.1006","Version":"17134.1006","ReleaseDate":"2019-09-10","Article":"KB4516058","Comment":""},{"Win10Version":"10.0.17763.737","Version":"17763.737","ReleaseDate":"2019-09-10","Article":"KB4512578","Comment":""},{"Win10Version":"10.0.18362.356","Version":"18362.356","ReleaseDate":"2019-09-10","Article":"KB4515384","Comment":""},{"Win10Version":"10.0.10240.18334","Version":"10240.18334","ReleaseDate":"2019-09-23","Article":"KB4522009","Comment":""},{"Win10Version":"10.0.14393.3206","Version":"14393.3206","ReleaseDate":"2019-09-23","Article":"KB4522010","Comment":""},{"Win10Version":"10.0.15063.2046","Version":"15063.2046","ReleaseDate":"2019-09-23","Article":"KB4522011","Comment":""},{"Win10Version":"10.0.16299.1392","Version":"16299.1392","ReleaseDate":"2019-09-23","Article":"KB4522012","Comment":""},{"Win10Version":"10.0.17134.1009","Version":"17134.1009","ReleaseDate":"2019-09-23","Article":"KB4522014","Comment":""},{"Win10Version":"10.0.17763.740","Version":"17763.740","ReleaseDate":"2019-09-23","Article":"KB4522015","Comment":""},{"Win10Version":"10.0.18362.357","Version":"18362.357","ReleaseDate":"2019-09-23","Article":"KB4522016","Comment":""},{"Win10Version":"10.0.14393.3242","Version":"14393.3242","ReleaseDate":"2019-09-24","Article":"KB4516061","Comment":""},{"Win10Version":"10.0.15063.2078","Version":"15063.2078","ReleaseDate":"2019-09-24","Article":"KB4516059","Comment":""},{"Win10Version":"10.0.16299.1420","Version":"16299.1420","ReleaseDate":"2019-09-24","Article":"KB4516071","Comment":""},{"Win10Version":"10.0.17134.1039","Version":"17134.1039","ReleaseDate":"2019-09-24","Article":"KB4516045","Comment":""},{"Win10Version":"10.0.17763.774","Version":"17763.774","ReleaseDate":"2019-09-24","Article":"KB4516077","Comment":""},{"Win10Version":"10.0.18362.387","Version":"18362.387","ReleaseDate":"2019-09-26","Article":"KB4517211","Comment":""},{"Win10Version":"10.0.10240.18335","Version":"10240.18335","ReleaseDate":"2019-10-03","Article":"KB4524153","Comment":""},{"Win10Version":"10.0.14393.3243","Version":"14393.3243","ReleaseDate":"2019-10-03","Article":"KB4524152","Comment":""},{"Win10Version":"10.0.15063.2079","Version":"15063.2079","ReleaseDate":"2019-10-03","Article":"KB4524151","Comment":""},{"Win10Version":"10.0.16299.1421","Version":"16299.1421","ReleaseDate":"2019-10-03","Article":"KB4524150","Comment":""},{"Win10Version":"10.0.17134.1040","Version":"17134.1040","ReleaseDate":"2019-10-03","Article":"KB4524149","Comment":""},{"Win10Version":"10.0.17763.775","Version":"17763.775","ReleaseDate":"2019-10-03","Article":"KB4524148","Comment":""},{"Win10Version":"10.0.18362.388","Version":"18362.388","ReleaseDate":"2019-10-03","Article":"KB4524147","Comment":""},{"Win10Version":"10.0.10240.18368","Version":"10240.18368","ReleaseDate":"2019-10-08","Article":"KB4520011","Comment":""},{"Win10Version":"10.0.14393.3274","Version":"14393.3274","ReleaseDate":"2019-10-08","Article":"KB4519998","Comment":""},{"Win10Version":"10.0.15063.2108","Version":"15063.2108","ReleaseDate":"2019-10-08","Article":"KB4520010","Comment":""},{"Win10Version":"10.0.15254.590","Version":"15254.590","ReleaseDate":"2019-10-08","Article":"KB4522809 Update for Windows 10 Mobile","Comment":""},{"Win10Version":"10.0.16299.1451","Version":"16299.1451","ReleaseDate":"2019-10-08","Article":"KB4520004","Comment":""},{"Win10Version":"10.0.17134.1069","Version":"17134.1069","ReleaseDate":"2019-10-08","Article":"KB4520008","Comment":""},{"Win10Version":"10.0.17763.805","Version":"17763.805","ReleaseDate":"2019-10-08","Article":"KB4519338","Comment":""},{"Win10Version":"10.0.18362.418","Version":"18362.418","ReleaseDate":"2019-10-08","Article":"KB4517389","Comment":""},{"Win10Version":"10.0.14393.3300","Version":"14393.3300","ReleaseDate":"2019-10-15","Article":"KB4519979","Comment":""},{"Win10Version":"10.0.16299.1481","Version":"16299.1481","ReleaseDate":"2019-10-15","Article":"KB4520006","Comment":""},{"Win10Version":"10.0.17134.1099","Version":"17134.1099","ReleaseDate":"2019-10-15","Article":"KB4519978","Comment":""},{"Win10Version":"10.0.17763.832","Version":"17763.832","ReleaseDate":"2019-10-15","Article":"KB4520062","Comment":""},{"Win10Version":"10.0.18362.449","Version":"18362.449","ReleaseDate":"2019-10-24","Article":"KB4522355","Comment":""},{"Win10Version":"10.0.10240.18395","Version":"10240.18395","ReleaseDate":"2019-11-12","Article":"KB4525232","Comment":""},{"Win10Version":"10.0.14393.3326","Version":"14393.3326","ReleaseDate":"2019-11-12","Article":"KB4525236","Comment":""},{"Win10Version":"10.0.15063.2172","Version":"15063.2172","ReleaseDate":"2019-11-12","Article":"KB4525245","Comment":""},{"Win10Version":"10.0.15254.597","Version":"15254.597","ReleaseDate":"2019-11-12","Article":"KB4522811 Update for Windows 10 Mobile","Comment":""},{"Win10Version":"10.0.16299.1508","Version":"16299.1508","ReleaseDate":"2019-11-12","Article":"KB4525241","Comment":""},{"Win10Version":"10.0.17134.1130","Version":"17134.1130","ReleaseDate":"2019-11-12","Article":"KB4525237","Comment":""},{"Win10Version":"10.0.17763.864","Version":"17763.864","ReleaseDate":"2019-11-12","Article":"KB4523205","Comment":""},{"Win10Version":"10.0.18362.476","Version":"18362.476","ReleaseDate":"2019-11-12","Article":"KB4524570","Comment":""},{"Win10Version":"10.0.18363.476","Version":"18363.476","ReleaseDate":"2019-11-12","Article":"KB4524570","Comment":""},{"Win10Version":"10.0.10240.18427","Version":"10240.18427","ReleaseDate":"2019-12-10","Article":"KB4530681","Comment":""},{"Win10Version":"10.0.14393.3384","Version":"14393.3384","ReleaseDate":"2019-12-10","Article":"KB4530689","Comment":""},{"Win10Version":"10.0.15063.2224","Version":"15063.2224","ReleaseDate":"2019-12-10","Article":"KB4530711","Comment":""},{"Win10Version":"10.0.15254.600","Version":"15254.600","ReleaseDate":"2019-12-10","Article":"KB4522812 Update for Windows 10 Mobile","Comment":""},{"Win10Version":"10.0.16299.1565","Version":"16299.1565","ReleaseDate":"2019-12-10","Article":"KB4530714","Comment":""},{"Win10Version":"10.0.17134.1184","Version":"17134.1184","ReleaseDate":"2019-12-10","Article":"KB4530717","Comment":""},{"Win10Version":"10.0.17763.914","Version":"17763.914","ReleaseDate":"2019-12-10","Article":"KB4530715","Comment":""},{"Win10Version":"10.0.18362.535","Version":"18362.535","ReleaseDate":"2019-12-10","Article":"KB4530684","Comment":""},{"Win10Version":"10.0.18363.535","Version":"18363.535","ReleaseDate":"2019-12-10","Article":"KB4530684","Comment":""},{"Win10Version":"10.0.10240.18453","Version":"10240.18453","ReleaseDate":"2020-01-14","Article":"KB4534306","Comment":""},{"Win10Version":"10.0.14393.3443","Version":"14393.3443","ReleaseDate":"2020-01-14","Article":"KB4534271","Comment":""},{"Win10Version":"10.0.15063.2254","Version":"15063.2254","ReleaseDate":"2020-01-14","Article":"KB4534296","Comment":""},{"Win10Version":"10.0.15254.603","Version":"15254.603","ReleaseDate":"2020-01-14","Article":"KB4535289 Update for Windows 10 Mobile","Comment":""},{"Win10Version":"10.0.16299.1625","Version":"16299.1625","ReleaseDate":"2020-01-14","Article":"KB4534276","Comment":""},{"Win10Version":"10.0.17134.1246","Version":"17134.1246","ReleaseDate":"2020-01-14","Article":"KB4534293","Comment":""},{"Win10Version":"10.0.17763.973","Version":"17763.973","ReleaseDate":"2020-01-14","Article":"KB4534273","Comment":""},{"Win10Version":"10.0.18362.592","Version":"18362.592","ReleaseDate":"2020-01-14","Article":"KB4528760","Comment":""},{"Win10Version":"10.0.18363.592","Version":"18363.592","ReleaseDate":"2020-01-14","Article":"KB4528760","Comment":""},{"Win10Version":"10.0.14393.3474","Version":"14393.3474","ReleaseDate":"2020-01-23","Article":"KB4534307","Comment":""},{"Win10Version":"10.0.16299.1654","Version":"16299.1654","ReleaseDate":"2020-01-23","Article":"KB4534318","Comment":""},{"Win10Version":"10.0.17134.1276","Version":"17134.1276","ReleaseDate":"2020-01-23","Article":"KB4534308","Comment":""},{"Win10Version":"10.0.17763.1012","Version":"17763.1012","ReleaseDate":"2020-01-23","Article":"KB4534321","Comment":""},{"Win10Version":"10.0.18362.628","Version":"18362.628","ReleaseDate":"2020-01-28","Article":"KB4532695","Comment":""},{"Win10Version":"10.0.18363.628","Version":"18363.628","ReleaseDate":"2020-01-28","Article":"KB4532695","Comment":""},{"Win10Version":"10.0.10240.18486","Version":"10240.18486","ReleaseDate":"2020-02-11","Article":"KB4537776","Comment":""},{"Win10Version":"10.0.14393.3504","Version":"14393.3504","ReleaseDate":"2020-02-11","Article":"KB4537764","Comment":""},{"Win10Version":"10.0.15063.2284","Version":"15063.2284","ReleaseDate":"2020-02-11","Article":"KB4537765","Comment":""},{"Win10Version":"10.0.16299.1686","Version":"16299.1686","ReleaseDate":"2020-02-11","Article":"KB4537789","Comment":""},{"Win10Version":"10.0.17134.1304","Version":"17134.1304","ReleaseDate":"2020-02-11","Article":"KB4537762","Comment":""},{"Win10Version":"10.0.17763.1039","Version":"17763.1039","ReleaseDate":"2020-02-11","Article":"KB4532691","Comment":""},{"Win10Version":"10.0.18362.657","Version":"18362.657","ReleaseDate":"2020-02-11","Article":"KB4532693","Comment":""},{"Win10Version":"10.0.18363.657","Version":"18363.657","ReleaseDate":"2020-02-11","Article":"KB4532693","Comment":""},{"Win10Version":"10.0.14393.3542","Version":"14393.3542","ReleaseDate":"2020-02-25","Article":"KB4537806","Comment":""},{"Win10Version":"10.0.16299.1717","Version":"16299.1717","ReleaseDate":"2020-02-25","Article":"KB4537816","Comment":""},{"Win10Version":"10.0.17134.1345","Version":"17134.1345","ReleaseDate":"2020-02-25","Article":"KB4537795","Comment":""},{"Win10Version":"10.0.17763.1075","Version":"17763.1075","ReleaseDate":"2020-02-25","Article":"KB4537818","Comment":""},{"Win10Version":"10.0.18362.693","Version":"18362.693","ReleaseDate":"2020-02-27","Article":"KB4535996","Comment":""},{"Win10Version":"10.0.18363.693","Version":"18363.693","ReleaseDate":"2020-02-27","Article":"KB4535996","Comment":""},{"Win10Version":"10.0.10240.18519","Version":"10240.18519","ReleaseDate":"2020-03-10","Article":"KB4540693","Comment":""},{"Win10Version":"10.0.14393.3564","Version":"14393.3564","ReleaseDate":"2020-03-10","Article":"KB4540670","Comment":""},{"Win10Version":"10.0.15063.2313","Version":"15063.2313","ReleaseDate":"2020-03-10","Article":"KB4540705","Comment":""},{"Win10Version":"10.0.16299.1747","Version":"16299.1747","ReleaseDate":"2020-03-10","Article":"KB4540681","Comment":""},{"Win10Version":"10.0.17134.1365","Version":"17134.1365","ReleaseDate":"2020-03-10","Article":"KB4540689","Comment":""},{"Win10Version":"10.0.17763.1098","Version":"17763.1098","ReleaseDate":"2020-03-10","Article":"KB4538461","Comment":""},{"Win10Version":"10.0.18362.719","Version":"18362.719","ReleaseDate":"2020-03-10","Article":"KB4540673","Comment":""},{"Win10Version":"10.0.18363.719","Version":"18363.719","ReleaseDate":"2020-03-10","Article":"KB4540673","Comment":""},{"Win10Version":"10.0.18362.720","Version":"18362.720","ReleaseDate":"2020-03-12","Article":"KB4551762","Comment":""},{"Win10Version":"10.0.18363.720","Version":"18363.720","ReleaseDate":"2020-03-12","Article":"KB4551762","Comment":""},{"Win10Version":"10.0.14393.3595","Version":"14393.3595","ReleaseDate":"2020-03-17","Article":"KB4541329","Comment":""},{"Win10Version":"10.0.16299.1775","Version":"16299.1775","ReleaseDate":"2020-03-17","Article":"KB4541330","Comment":""},{"Win10Version":"10.0.17134.1399","Version":"17134.1399","ReleaseDate":"2020-03-17","Article":"KB4541333","Comment":""},{"Win10Version":"10.0.17763.1131","Version":"17763.1131","ReleaseDate":"2020-03-17","Article":"KB4541331","Comment":""},{"Win10Version":"10.0.18362.752","Version":"18362.752","ReleaseDate":"2020-03-24","Article":"KB4541335","Comment":""},{"Win10Version":"10.0.18363.752","Version":"18363.752","ReleaseDate":"2020-03-24","Article":"KB4541335","Comment":""},{"Win10Version":"10.0.16299.1776","Version":"16299.1776","ReleaseDate":"2020-03-30","Article":"KB4554342","Comment":""},{"Win10Version":"10.0.17134.1401","Version":"17134.1401","ReleaseDate":"2020-03-30","Article":"KB4554349","Comment":""},{"Win10Version":"10.0.17763.1132","Version":"17763.1132","ReleaseDate":"2020-03-30","Article":"KB4554354","Comment":""},{"Win10Version":"10.0.18362.753","Version":"18362.753","ReleaseDate":"2020-03-30","Article":"KB4554364","Comment":""},{"Win10Version":"10.0.18363.753","Version":"18363.753","ReleaseDate":"2020-03-30","Article":"KB4554364","Comment":""},{"Win10Version":"10.0.10240.18545","Version":"10240.18545","ReleaseDate":"2020-04-14","Article":"KB4550930","Comment":""},{"Win10Version":"10.0.14393.3630","Version":"14393.3630","ReleaseDate":"2020-04-14","Article":"KB4550929","Comment":""},{"Win10Version":"10.0.15063.2346","Version":"15063.2346","ReleaseDate":"2020-04-14","Article":"KB4550939","Comment":""},{"Win10Version":"10.0.16299.1806","Version":"16299.1806","ReleaseDate":"2020-04-14","Article":"KB4550927","Comment":""},{"Win10Version":"10.0.17134.1425","Version":"17134.1425","ReleaseDate":"2020-04-14","Article":"KB4550922","Comment":""},{"Win10Version":"10.0.17763.1158","Version":"17763.1158","ReleaseDate":"2020-04-14","Article":"KB4549949","Comment":""},{"Win10Version":"10.0.18362.778","Version":"18362.778","ReleaseDate":"2020-04-14","Article":"KB4549951","Comment":""},{"Win10Version":"10.0.18363.778","Version":"18363.778","ReleaseDate":"2020-04-14","Article":"KB4549951","Comment":""},{"Win10Version":"10.0.14393.3659","Version":"14393.3659","ReleaseDate":"2020-04-21","Article":"KB4550947","Comment":""},{"Win10Version":"10.0.17134.1456","Version":"17134.1456","ReleaseDate":"2020-04-21","Article":"KB4550944","Comment":""},{"Win10Version":"10.0.17763.1192","Version":"17763.1192","ReleaseDate":"2020-04-21","Article":"KB4550969","Comment":""},{"Win10Version":"10.0.18362.815","Version":"18362.815","ReleaseDate":"2020-04-21","Article":"KB4550945","Comment":""},{"Win10Version":"10.0.18363.815","Version":"18363.815","ReleaseDate":"2020-04-21","Article":"KB4550945","Comment":""},{"Win10Version":"10.0.10240.18575","Version":"10240.18575","ReleaseDate":"2020-05-12","Article":"KB4556826","Comment":""},{"Win10Version":"10.0.14393.3686","Version":"14393.3686","ReleaseDate":"2020-05-12","Article":"KB4556813","Comment":""},{"Win10Version":"10.0.15063.2375","Version":"15063.2375","ReleaseDate":"2020-05-12","Article":"KB4556804","Comment":""},{"Win10Version":"10.0.16299.1868","Version":"16299.1868","ReleaseDate":"2020-05-12","Article":"KB4556812","Comment":""},{"Win10Version":"10.0.17134.1488","Version":"17134.1488","ReleaseDate":"2020-05-12","Article":"KB4556807","Comment":""},{"Win10Version":"10.0.17763.1217","Version":"17763.1217","ReleaseDate":"2020-05-12","Article":"KB4551853","Comment":""},{"Win10Version":"10.0.18362.836","Version":"18362.836","ReleaseDate":"2020-05-12","Article":"KB4556799","Comment":""},{"Win10Version":"10.0.18363.836","Version":"18363.836","ReleaseDate":"2020-05-12","Article":"KB4556799","Comment":""},{"Win10Version":"10.0.10240.18608","Version":"10240.18608","ReleaseDate":"2020-06-09","Article":"KB4561649","Comment":""},{"Win10Version":"10.0.14393.3750","Version":"14393.3750","ReleaseDate":"2020-06-09","Article":"KB4561616","Comment":""},{"Win10Version":"10.0.15063.2409","Version":"15063.2409","ReleaseDate":"2020-06-09","Article":"KB4561605","Comment":""},{"Win10Version":"10.0.16299.1932","Version":"16299.1932","ReleaseDate":"2020-06-09","Article":"KB4561602","Comment":""},{"Win10Version":"10.0.17134.1550","Version":"17134.1550","ReleaseDate":"2020-06-09","Article":"KB4561621","Comment":""},{"Win10Version":"10.0.17763.1282","Version":"17763.1282","ReleaseDate":"2020-06-09","Article":"KB4561608","Comment":""},{"Win10Version":"10.0.18362.900","Version":"18362.900","ReleaseDate":"2020-06-09","Article":"KB4560960","Comment":""},{"Win10Version":"10.0.18363.900","Version":"18363.900","ReleaseDate":"2020-06-09","Article":"KB4560960","Comment":""},{"Win10Version":"10.0.19041.329","Version":"19041.329","ReleaseDate":"2020-06-09","Article":"KB4557957","Comment":""},{"Win10Version":"10.0.17134.1553","Version":"17134.1553","ReleaseDate":"2020-06-16","Article":"KB4567514","Comment":""},{"Win10Version":"10.0.17763.1294","Version":"17763.1294","ReleaseDate":"2020-06-16","Article":"KB4567513","Comment":""},{"Win10Version":"10.0.18362.904","Version":"18362.904","ReleaseDate":"2020-06-16","Article":"KB4567512","Comment":""},{"Win10Version":"10.0.18363.904","Version":"18363.904","ReleaseDate":"2020-06-16","Article":"KB4567512","Comment":""},{"Win10Version":"10.0.10240.18609","Version":"10240.18609","ReleaseDate":"2020-06-18","Article":"KB4567518","Comment":""},{"Win10Version":"10.0.14393.3755","Version":"14393.3755","ReleaseDate":"2020-06-18","Article":"KB4567517","Comment":""},{"Win10Version":"10.0.15063.2411","Version":"15063.2411","ReleaseDate":"2020-06-18","Article":"KB4567516","Comment":""},{"Win10Version":"10.0.16299.1937","Version":"16299.1937","ReleaseDate":"2020-06-18","Article":"KB4567515","Comment":""},{"Win10Version":"10.0.19041.331","Version":"19041.331","ReleaseDate":"2020-06-18","Article":"KB4567523","Comment":""},{"Win10Version":"10.0.10240.18638","Version":"10240.18638","ReleaseDate":"2020-07-14","Article":"KB4565513","Comment":""},{"Win10Version":"10.0.14393.3808","Version":"14393.3808","ReleaseDate":"2020-07-14","Article":"KB4565511","Comment":""},{"Win10Version":"10.0.15063.2439","Version":"15063.2439","ReleaseDate":"2020-07-14","Article":"KB4565499","Comment":""},{"Win10Version":"10.0.16299.1992","Version":"16299.1992","ReleaseDate":"2020-07-14","Article":"KB4565508","Comment":""},{"Win10Version":"10.0.17134.1610","Version":"17134.1610","ReleaseDate":"2020-07-14","Article":"KB4565489","Comment":""},{"Win10Version":"10.0.17763.1339","Version":"17763.1339","ReleaseDate":"2020-07-14","Article":"KB4558998","Comment":""},{"Win10Version":"10.0.18362.959","Version":"18362.959","ReleaseDate":"2020-07-14","Article":"KB4565483","Comment":""},{"Win10Version":"10.0.18363.959","Version":"18363.959","ReleaseDate":"2020-07-14","Article":"KB4565483","Comment":""},{"Win10Version":"10.0.19041.388","Version":"19041.388","ReleaseDate":"2020-07-14","Article":"KB4565503","Comment":""},{"Win10Version":"10.0.17763.1369","Version":"17763.1369","ReleaseDate":"2020-07-21","Article":"KB4559003","Comment":""},{"Win10Version":"10.0.18362.997","Version":"18362.997","ReleaseDate":"2020-07-21","Article":"KB4559004","Comment":""},{"Win10Version":"10.0.18363.997","Version":"18363.997","ReleaseDate":"2020-07-21","Article":"KB4559004","Comment":""},{"Win10Version":"10.0.19041.423","Version":"19041.423","ReleaseDate":"2020-07-31","Article":"KB4568831","Comment":""},{"Win10Version":"10.0.10240.18666","Version":"10240.18666","ReleaseDate":"2020-08-11","Article":"KB4571692","Comment":""},{"Win10Version":"10.0.14393.3866","Version":"14393.3866","ReleaseDate":"2020-08-11","Article":"KB4571694","Comment":""},{"Win10Version":"10.0.15063.2467","Version":"15063.2467","ReleaseDate":"2020-08-11","Article":"KB4571689","Comment":""},{"Win10Version":"10.0.16299.2045","Version":"16299.2045","ReleaseDate":"2020-08-11","Article":"KB4571741","Comment":""},{"Win10Version":"10.0.17134.1667","Version":"17134.1667","ReleaseDate":"2020-08-11","Article":"KB4571709","Comment":""},{"Win10Version":"10.0.17763.1397","Version":"17763.1397","ReleaseDate":"2020-08-11","Article":"KB4565349","Comment":""},{"Win10Version":"10.0.18362.1016","Version":"18362.1016","ReleaseDate":"2020-08-11","Article":"KB4565351","Comment":""},{"Win10Version":"10.0.18363.1016","Version":"18363.1016","ReleaseDate":"2020-08-11","Article":"KB4565351","Comment":""},{"Win10Version":"10.0.19041.450","Version":"19041.450","ReleaseDate":"2020-08-11","Article":"KB4566782","Comment":""},{"Win10Version":"10.0.17763.1432","Version":"17763.1432","ReleaseDate":"2020-08-20","Article":"KB4571748","Comment":"Preview"},{"Win10Version":"10.0.18362.1049","Version":"18362.1049","ReleaseDate":"2020-08-20","Article":"KB4566116","Comment":"Preview"},{"Win10Version":"10.0.18363.1049","Version":"18363.1049","ReleaseDate":"2020-08-20","Article":"KB4566116","Comment":"Preview"},{"Win10Version":"10.0.19041.488","Version":"19041.488","ReleaseDate":"2020-09-03","Article":"KB4571744","Comment":"Preview"},{"Win10Version":"10.0.10240.18696","Version":"10240.18696","ReleaseDate":"2020-09-08","Article":"KB4577049","Comment":""},{"Win10Version":"10.0.14393.3930","Version":"14393.3930","ReleaseDate":"2020-09-08","Article":"KB4577015","Comment":""},{"Win10Version":"10.0.15063.2500","Version":"15063.2500","ReleaseDate":"2020-09-08","Article":"KB4577021","Comment":""},{"Win10Version":"10.0.16299.2107","Version":"16299.2107","ReleaseDate":"2020-09-08","Article":"KB4577041","Comment":""},{"Win10Version":"10.0.17134.1726","Version":"17134.1726","ReleaseDate":"2020-09-08","Article":"KB4577032","Comment":""},{"Win10Version":"10.0.17763.1457","Version":"17763.1457","ReleaseDate":"2020-09-08","Article":"KB4570333","Comment":""},{"Win10Version":"10.0.18362.1082","Version":"18362.1082","ReleaseDate":"2020-09-08","Article":"KB4574727","Comment":""},{"Win10Version":"10.0.18363.1082","Version":"18363.1082","ReleaseDate":"2020-09-08","Article":"KB4574727","Comment":""},{"Win10Version":"10.0.19041.508","Version":"19041.508","ReleaseDate":"2020-09-08","Article":"KB4571756","Comment":""},{"Win10Version":"10.0.17763.1490","Version":"17763.1490","ReleaseDate":"2020-09-16","Article":"KB4577069","Comment":"Preview"},{"Win10Version":"10.0.18362.1110","Version":"18362.1110","ReleaseDate":"2020-09-16","Article":"KB4577062","Comment":"Preview"},{"Win10Version":"10.0.18363.1110","Version":"18363.1110","ReleaseDate":"2020-09-16","Article":"KB4577062","Comment":"Preview"},{"Win10Version":"10.0.19041.546","Version":"19041.546","ReleaseDate":"2020-10-01","Article":"KB4577063","Comment":"Preview"},{"Win10Version":"10.0.10240.18725","Version":"10240.18725","ReleaseDate":"2020-10-13","Article":"KB4580327","Comment":""},{"Win10Version":"10.0.14393.3986","Version":"14393.3986","ReleaseDate":"2020-10-13","Article":"KB4580346","Comment":""},{"Win10Version":"10.0.15063.2525","Version":"15063.2525","ReleaseDate":"2020-10-13","Article":"KB4580370","Comment":""},{"Win10Version":"10.0.16299.2166","Version":"16299.2166","ReleaseDate":"2020-10-13","Article":"KB4580328","Comment":""},{"Win10Version":"10.0.17134.1792","Version":"17134.1792","ReleaseDate":"2020-10-13","Article":"KB4580330","Comment":""},{"Win10Version":"10.0.17763.1518","Version":"17763.1518","ReleaseDate":"2020-10-13","Article":"KB4577668","Comment":""},{"Win10Version":"10.0.18362.1139","Version":"18362.1139","ReleaseDate":"2020-10-13","Article":"KB4577671","Comment":""},{"Win10Version":"10.0.18363.1139","Version":"18363.1139","ReleaseDate":"2020-10-13","Article":"KB4577671","Comment":""},{"Win10Version":"10.0.19041.572","Version":"19041.572","ReleaseDate":"2020-10-13","Article":"KB4579311","Comment":""},{"Win10Version":"10.0.17763.1554","Version":"17763.1554","ReleaseDate":"2020-10-20","Article":"KB4580390","Comment":"Preview"},{"Win10Version":"10.0.18362.1171","Version":"18362.1171","ReleaseDate":"2020-10-20","Article":"KB4580386","Comment":"Preview"},{"Win10Version":"10.0.18363.1171","Version":"18363.1171","ReleaseDate":"2020-10-20","Article":"KB4580386","Comment":"Preview"},{"Win10Version":"10.0.19041.610","Version":"19041.610","ReleaseDate":"2020-10-29","Article":"KB4580364","Comment":"Preview"},{"Win10Version":"10.0.19042.610","Version":"19042.610","ReleaseDate":"2020-10-29","Article":"KB4580364","Comment":"Preview"},{"Win10Version":"10.0.10240.18756","Version":"10240.18756","ReleaseDate":"2020-11-10","Article":"KB4586787","Comment":""},{"Win10Version":"10.0.14393.4046","Version":"14393.4046","ReleaseDate":"2020-11-10","Article":"KB4586830","Comment":""},{"Win10Version":"10.0.15063.2554","Version":"15063.2554","ReleaseDate":"2020-11-10","Article":"KB4586782","Comment":""},{"Win10Version":"10.0.17134.1845","Version":"17134.1845","ReleaseDate":"2020-11-10","Article":"KB4586785","Comment":""},{"Win10Version":"10.0.17763.1577","Version":"17763.1577","ReleaseDate":"2020-11-10","Article":"KB4586793","Comment":""},{"Win10Version":"10.0.18362.1198","Version":"18362.1198","ReleaseDate":"2020-11-10","Article":"KB4586786","Comment":""},{"Win10Version":"10.0.18363.1198","Version":"18363.1198","ReleaseDate":"2020-11-10","Article":"KB4586786","Comment":""},{"Win10Version":"10.0.19041.630","Version":"19041.630","ReleaseDate":"2020-11-10","Article":"KB4586781","Comment":""},{"Win10Version":"10.0.19042.630","Version":"19042.630","ReleaseDate":"2020-11-10","Article":"KB4586781","Comment":""},{"Win10Version":"10.0.17763.1579","Version":"17763.1579","ReleaseDate":"2020-11-17","Article":"KB4594442","Comment":"Out-of-band"},{"Win10Version":"10.0.14393.4048","Version":"14393.4048","ReleaseDate":"2020-11-19","Article":"KB4594441","Comment":"Out-of-band"},{"Win10Version":"10.0.17763.1613","Version":"17763.1613","ReleaseDate":"2020-11-19","Article":"KB4586839","Comment":"Preview"},{"Win10Version":"10.0.18362.1199","Version":"18362.1199","ReleaseDate":"2020-11-19","Article":"KB4594443","Comment":"Out-of-band"},{"Win10Version":"10.0.18362.1237","Version":"18362.1237","ReleaseDate":"2020-11-19","Article":"KB4586819","Comment":"Preview"},{"Win10Version":"10.0.18363.1199","Version":"18363.1199","ReleaseDate":"2020-11-19","Article":"KB4594443","Comment":"Out-of-band"},{"Win10Version":"10.0.18363.1237","Version":"18363.1237","ReleaseDate":"2020-11-19","Article":"KB4586819","Comment":"Preview"},{"Win10Version":"10.0.19041.631","Version":"19041.631","ReleaseDate":"2020-11-19","Article":"KB4594440","Comment":"Out-of-band"},{"Win10Version":"10.0.19042.631","Version":"19042.631","ReleaseDate":"2020-11-19","Article":"KB4594440","Comment":"Out-of-band"},{"Win10Version":"10.0.19041.662","Version":"19041.662","ReleaseDate":"2020-11-30","Article":"KB4586853","Comment":"Preview"},{"Win10Version":"10.0.19042.662","Version":"19042.662","ReleaseDate":"2020-11-30","Article":"KB4586853","Comment":"Preview"},{"Win10Version":"10.0.10240.18782","Version":"10240.18782","ReleaseDate":"2020-12-08","Article":"KB4592464","Comment":""},{"Win10Version":"10.0.14393.4104","Version":"14393.4104","ReleaseDate":"2020-12-08","Article":"KB4593226","Comment":""},{"Win10Version":"10.0.15063.2584","Version":"15063.2584","ReleaseDate":"2020-12-08","Article":"KB4592473","Comment":""},{"Win10Version":"10.0.17134.1902","Version":"17134.1902","ReleaseDate":"2020-12-08","Article":"KB4592446","Comment":""},{"Win10Version":"10.0.17763.1637","Version":"17763.1637","ReleaseDate":"2020-12-08","Article":"KB4592440","Comment":""},{"Win10Version":"10.0.18362.1256","Version":"18362.1256","ReleaseDate":"2020-12-08","Article":"KB4592449","Comment":""},{"Win10Version":"10.0.18363.1256","Version":"18363.1256","ReleaseDate":"2020-12-08","Article":"KB4592449","Comment":""},{"Win10Version":"10.0.19041.685","Version":"19041.685","ReleaseDate":"2020-12-08","Article":"KB4592438","Comment":""},{"Win10Version":"10.0.19042.685","Version":"19042.685","ReleaseDate":"2020-12-08","Article":"KB4592438","Comment":""},{"Win10Version":"10.0.10240.18818","Version":"10240.18818","ReleaseDate":"2021-01-12","Article":"KB4598231","Comment":""},{"Win10Version":"10.0.14393.4169","Version":"14393.4169","ReleaseDate":"2021-01-12","Article":"KB4598243","Comment":""},{"Win10Version":"10.0.15063.2614","Version":"15063.2614","ReleaseDate":"2021-01-12","Article":"KB4599208","Comment":""},{"Win10Version":"10.0.17134.1967","Version":"17134.1967","ReleaseDate":"2021-01-12","Article":"KB4598245","Comment":""},{"Win10Version":"10.0.17763.1697","Version":"17763.1697","ReleaseDate":"2021-01-12","Article":"KB4598230","Comment":""},{"Win10Version":"10.0.18363.1316","Version":"18363.1316","ReleaseDate":"2021-01-12","Article":"KB4598229","Comment":""},{"Win10Version":"10.0.19041.746","Version":"19041.746","ReleaseDate":"2021-01-12","Article":"KB4598242","Comment":""},{"Win10Version":"10.0.19042.746","Version":"19042.746","ReleaseDate":"2021-01-12","Article":"KB4598242","Comment":""},{"Win10Version":"10.0.17763.1728","Version":"17763.1728","ReleaseDate":"2021-01-21","Article":"KB4598296","Comment":"Preview"},{"Win10Version":"10.0.18363.1350","Version":"18363.1350","ReleaseDate":"2021-01-21","Article":"KB4598298","Comment":"Preview"},{"Win10Version":"10.0.19041.789","Version":"19041.789","ReleaseDate":"2021-02-02","Article":"KB4598291","Comment":"Preview"},{"Win10Version":"10.0.19042.789","Version":"19042.789","ReleaseDate":"2021-02-02","Article":"KB4598291","Comment":"Preview"},{"Win10Version":"10.0.10240.18842","Version":"10240.18842","ReleaseDate":"2021-02-09","Article":"KB4601331","Comment":""},{"Win10Version":"10.0.14393.4225","Version":"14393.4225","ReleaseDate":"2021-02-09","Article":"KB4601318","Comment":""},{"Win10Version":"10.0.15063.2642","Version":"15063.2642","ReleaseDate":"2021-02-09","Article":"KB4601330","Comment":""},{"Win10Version":"10.0.17134.2026","Version":"17134.2026","ReleaseDate":"2021-02-09","Article":"KB4601354","Comment":""},{"Win10Version":"10.0.17763.1757","Version":"17763.1757","ReleaseDate":"2021-02-09","Article":"KB4601345","Comment":""},{"Win10Version":"10.0.18363.1377","Version":"18363.1377","ReleaseDate":"2021-02-09","Article":"KB4601315","Comment":""},{"Win10Version":"10.0.19041.804","Version":"19041.804","ReleaseDate":"2021-02-09","Article":"KB4601319","Comment":""},{"Win10Version":"10.0.19042.804","Version":"19042.804","ReleaseDate":"2021-02-09","Article":"KB4601319","Comment":""},{"Win10Version":"10.0.18363.1379","Version":"18363.1379","ReleaseDate":"2021-02-11","Article":"KB5001028","Comment":"Out-of-band"},{"Win10Version":"10.0.17763.1790","Version":"17763.1790","ReleaseDate":"2021-02-16","Article":"KB4601383","Comment":"Preview"},{"Win10Version":"10.0.18363.1411","Version":"18363.1411","ReleaseDate":"2021-02-16","Article":"KB4601380","Comment":"Preview"},{"Win10Version":"10.0.19041.844","Version":"19041.844","ReleaseDate":"2021-02-24","Article":"KB4601382","Comment":"Preview"},{"Win10Version":"10.0.19042.844","Version":"19042.844","ReleaseDate":"2021-02-24","Article":"KB4601382","Comment":"Preview"},{"Win10Version":"10.0.10240.18874","Version":"10240.18874","ReleaseDate":"2021-03-09","Article":"KB5000807","Comment":""},{"Win10Version":"10.0.14393.4283","Version":"14393.4283","ReleaseDate":"2021-03-09","Article":"KB5000803","Comment":""},{"Win10Version":"10.0.15063.2679","Version":"15063.2679","ReleaseDate":"2021-03-09","Article":"KB5000812","Comment":""},{"Win10Version":"10.0.17134.2087","Version":"17134.2087","ReleaseDate":"2021-03-09","Article":"KB5000809","Comment":""},{"Win10Version":"10.0.17763.1817","Version":"17763.1817","ReleaseDate":"2021-03-09","Article":"KB5000822","Comment":""},{"Win10Version":"10.0.18363.1440","Version":"18363.1440","ReleaseDate":"2021-03-09","Article":"KB5000808","Comment":""},{"Win10Version":"10.0.19041.867","Version":"19041.867","ReleaseDate":"2021-03-09","Article":"KB5000802","Comment":""},{"Win10Version":"10.0.19042.867","Version":"19042.867","ReleaseDate":"2021-03-09","Article":"KB5000802","Comment":""},{"Win10Version":"10.0.17134.2088","Version":"17134.2088","ReleaseDate":"2021-03-15","Article":"KB5001565","Comment":"Out-of-band"},{"Win10Version":"10.0.17763.1821","Version":"17763.1821","ReleaseDate":"2021-03-15","Article":"KB5001568","Comment":"Out-of-band"},{"Win10Version":"10.0.18363.1441","Version":"18363.1441","ReleaseDate":"2021-03-15","Article":"KB5001566","Comment":"Out-of-band"},{"Win10Version":"10.0.19041.868","Version":"19041.868","ReleaseDate":"2021-03-15","Article":"KB5001567","Comment":"Out-of-band"},{"Win10Version":"10.0.19042.868","Version":"19042.868","ReleaseDate":"2021-03-15","Article":"KB5001567","Comment":"Out-of-band"},{"Win10Version":"10.0.10240.18875","Version":"10240.18875","ReleaseDate":"2021-03-18","Article":"KB5001631","Comment":"Out-of-band"},{"Win10Version":"10.0.14393.4288","Version":"14393.4288","ReleaseDate":"2021-03-18","Article":"KB5001633","Comment":"Out-of-band"},{"Win10Version":"10.0.17134.2090","Version":"17134.2090","ReleaseDate":"2021-03-18","Article":"KB5001634","Comment":"Out-of-band"},{"Win10Version":"10.0.17763.1823","Version":"17763.1823","ReleaseDate":"2021-03-18","Article":"KB5001638","Comment":"Out-of-band"},{"Win10Version":"10.0.18363.1443","Version":"18363.1443","ReleaseDate":"2021-03-18","Article":"KB5001648","Comment":"Out-of-band"},{"Win10Version":"10.0.19041.870","Version":"19041.870","ReleaseDate":"2021-03-18","Article":"KB5001649","Comment":"Out-of-band"},{"Win10Version":"10.0.19042.870","Version":"19042.870","ReleaseDate":"2021-03-18","Article":"KB5001649","Comment":"Out-of-band"},{"Win10Version":"10.0.17763.1852","Version":"17763.1852","ReleaseDate":"2021-03-25","Article":"KB5000854","Comment":"Preview"},{"Win10Version":"10.0.18363.1474","Version":"18363.1474","ReleaseDate":"2021-03-25","Article":"KB5000850","Comment":"Preview"},{"Win10Version":"10.0.19041.906","Version":"19041.906","ReleaseDate":"2021-03-29","Article":"KB5000842","Comment":"Preview"},{"Win10Version":"10.0.19042.906","Version":"19042.906","ReleaseDate":"2021-03-29","Article":"KB5000842","Comment":"Preview"},{"Win10Version":"10.0.10240.18906","Version":"10240.18906","ReleaseDate":"2021-04-13","Article":"KB5001340","Comment":""},{"Win10Version":"10.0.14393.4350","Version":"14393.4350","ReleaseDate":"2021-04-13","Article":"KB5001347","Comment":""},{"Win10Version":"10.0.17134.2145","Version":"17134.2145","ReleaseDate":"2021-04-13","Article":"KB5001339","Comment":""},{"Win10Version":"10.0.17763.1879","Version":"17763.1879","ReleaseDate":"2021-04-13","Article":"KB5001342","Comment":""},{"Win10Version":"10.0.18363.1500","Version":"18363.1500","ReleaseDate":"2021-04-13","Article":"KB5001337","Comment":""},{"Win10Version":"10.0.19041.928","Version":"19041.928","ReleaseDate":"2021-04-13","Article":"KB5001330","Comment":""},{"Win10Version":"10.0.19042.928","Version":"19042.928","ReleaseDate":"2021-04-13","Article":"KB5001330","Comment":""},{"Win10Version":"10.0.17763.1911","Version":"17763.1911","ReleaseDate":"2021-04-22","Article":"KB5001384","Comment":"Preview"},{"Win10Version":"10.0.18363.1533","Version":"18363.1533","ReleaseDate":"2021-04-22","Article":"KB5001396","Comment":"Preview"},{"Win10Version":"10.0.19041.964","Version":"19041.964","ReleaseDate":"2021-04-28","Article":"KB5001391","Comment":"Preview"},{"Win10Version":"10.0.19042.964","Version":"19042.964","ReleaseDate":"2021-04-28","Article":"KB5001391","Comment":"Preview"},{"Win10Version":"10.0.10240.18932","Version":"10240.18932","ReleaseDate":"2021-05-11","Article":"KB5003172","Comment":""},{"Win10Version":"10.0.14393.4402","Version":"14393.4402","ReleaseDate":"2021-05-11","Article":"KB5003197","Comment":""},{"Win10Version":"10.0.17134.2208","Version":"17134.2208","ReleaseDate":"2021-05-11","Article":"KB5003174","Comment":""},{"Win10Version":"10.0.17763.1935","Version":"17763.1935","ReleaseDate":"2021-05-11","Article":"KB5003171","Comment":""},{"Win10Version":"10.0.18363.1556","Version":"18363.1556","ReleaseDate":"2021-05-11","Article":"KB5003169","Comment":""},{"Win10Version":"10.0.19041.985","Version":"19041.985","ReleaseDate":"2021-05-11","Article":"KB5003173","Comment":""},{"Win10Version":"10.0.19042.985","Version":"19042.985","ReleaseDate":"2021-05-11","Article":"KB5003173","Comment":""},{"Win10Version":"10.0.19043.985","Version":"19043.985","ReleaseDate":"2021-05-11","Article":"KB5003173","Comment":""},{"Win10Version":"10.0.17763.1971","Version":"17763.1971","ReleaseDate":"2021-05-20","Article":"KB5003217","Comment":"Preview"},{"Win10Version":"10.0.18363.1593","Version":"18363.1593","ReleaseDate":"2021-05-20","Article":"KB5003212","Comment":"Preview"},{"Win10Version":"10.0.19041.1023","Version":"19041.1023","ReleaseDate":"2021-05-25","Article":"KB5003214","Comment":"Preview"},{"Win10Version":"10.0.19042.1023","Version":"19042.1023","ReleaseDate":"2021-05-25","Article":"KB5003214","Comment":"Preview"},{"Win10Version":"10.0.19043.1023","Version":"19043.1023","ReleaseDate":"2021-05-25","Article":"KB5003214","Comment":"Preview"},{"Win10Version":"10.0.10240.18967","Version":"10240.18967","ReleaseDate":"2021-06-08","Article":"KB5003687","Comment":""},{"Win10Version":"10.0.14393.4467","Version":"14393.4467","ReleaseDate":"2021-06-08","Article":"KB5003638","Comment":""},{"Win10Version":"10.0.17763.1999","Version":"17763.1999","ReleaseDate":"2021-06-08","Article":"KB5003646","Comment":""},{"Win10Version":"10.0.18363.1621","Version":"18363.1621","ReleaseDate":"2021-06-08","Article":"KB5003635","Comment":""},{"Win10Version":"10.0.19041.1052","Version":"19041.1052","ReleaseDate":"2021-06-08","Article":"KB5003637","Comment":""},{"Win10Version":"10.0.19042.1052","Version":"19042.1052","ReleaseDate":"2021-06-08","Article":"KB5003637","Comment":""},{"Win10Version":"10.0.19043.1052","Version":"19043.1052","ReleaseDate":"2021-06-08","Article":"KB5003637","Comment":""},{"Win10Version":"10.0.19041.1055","Version":"19041.1055","ReleaseDate":"2021-06-11","Article":"KB5004476","Comment":"Out-of-band"},{"Win10Version":"10.0.19042.1055","Version":"19042.1055","ReleaseDate":"2021-06-11","Article":"KB5004476","Comment":"Out-of-band"},{"Win10Version":"10.0.19043.1055","Version":"19043.1055","ReleaseDate":"2021-06-11","Article":"KB5004476","Comment":"Out-of-band"},{"Win10Version":"10.0.17763.2028","Version":"17763.2028","ReleaseDate":"2021-06-15","Article":"KB5003703","Comment":"Preview"},{"Win10Version":"10.0.18363.1645","Version":"18363.1645","ReleaseDate":"2021-06-15","Article":"KB5003698","Comment":"Preview"},{"Win10Version":"10.0.19041.1081","Version":"19041.1081","ReleaseDate":"2021-06-21","Article":"KB5003690","Comment":"Preview"},{"Win10Version":"10.0.19042.1081","Version":"19042.1081","ReleaseDate":"2021-06-21","Article":"KB5003690","Comment":"Preview"},{"Win10Version":"10.0.19043.1081","Version":"19043.1081","ReleaseDate":"2021-06-21","Article":"KB5003690","Comment":"Preview"},{"Win10Version":"10.0.19041.1082","Version":"19041.1082","ReleaseDate":"2021-06-29","Article":"KB5004760","Comment":"Out-of-band"},{"Win10Version":"10.0.19042.1082","Version":"19042.1082","ReleaseDate":"2021-06-29","Article":"KB5004760","Comment":"Out-of-band"},{"Win10Version":"10.0.19043.1082","Version":"19043.1082","ReleaseDate":"2021-06-29","Article":"KB5004760","Comment":"Out-of-band"},{"Win10Version":"10.0.10240.18969","Version":"10240.18969","ReleaseDate":"2021-07-06","Article":"KB5004950","Comment":"Out-of-band"},{"Win10Version":"10.0.17763.2029","Version":"17763.2029","ReleaseDate":"2021-07-06","Article":"KB5004947","Comment":"Out-of-band"},{"Win10Version":"10.0.18363.1646","Version":"18363.1646","ReleaseDate":"2021-07-06","Article":"KB5004946","Comment":"Out-of-band"},{"Win10Version":"10.0.19041.1083","Version":"19041.1083","ReleaseDate":"2021-07-06","Article":"KB5004945","Comment":"Out-of-band"},{"Win10Version":"10.0.19042.1083","Version":"19042.1083","ReleaseDate":"2021-07-06","Article":"KB5004945","Comment":"Out-of-band"},{"Win10Version":"10.0.19043.1083","Version":"19043.1083","ReleaseDate":"2021-07-06","Article":"KB5004945","Comment":"Out-of-band"},{"Win10Version":"10.0.14393.4470","Version":"14393.4470","ReleaseDate":"2021-07-07","Article":"KB5004948","Comment":"Out-of-band"},{"Win10Version":"10.0.10240.19003","Version":"10240.19003","ReleaseDate":"2021-07-13","Article":"KB5004249","Comment":""},{"Win10Version":"10.0.14393.4530","Version":"14393.4530","ReleaseDate":"2021-07-13","Article":"KB5004238","Comment":""},{"Win10Version":"10.0.17763.2061","Version":"17763.2061","ReleaseDate":"2021-07-13","Article":"KB5004244","Comment":""},{"Win10Version":"10.0.18363.1679","Version":"18363.1679","ReleaseDate":"2021-07-13","Article":"KB5004245","Comment":""},{"Win10Version":"10.0.19041.1110","Version":"19041.1110","ReleaseDate":"2021-07-13","Article":"KB5004237","Comment":""},{"Win10Version":"10.0.19042.1110","Version":"19042.1110","ReleaseDate":"2021-07-13","Article":"KB5004237","Comment":""},{"Win10Version":"10.0.19043.1110","Version":"19043.1110","ReleaseDate":"2021-07-13","Article":"KB5004237","Comment":""},{"Win10Version":"10.0.17763.2090","Version":"17763.2090","ReleaseDate":"2021-07-20","Article":"KB5004308","Comment":"Preview"},{"Win10Version":"10.0.17763.2091","Version":"17763.2091","ReleaseDate":"2021-07-27","Article":"KB5005394","Comment":"Out-of-band"},{"Win10Version":"10.0.14393.4532","Version":"14393.4532","ReleaseDate":"2021-07-29","Article":"KB5005393","Comment":"Out-of-band"},{"Win10Version":"10.0.18363.1714","Version":"18363.1714","ReleaseDate":"2021-07-29","Article":"KB5004293","Comment":"Preview"},{"Win10Version":"10.0.19041.1151","Version":"19041.1151","ReleaseDate":"2021-07-29","Article":"KB5004296","Comment":"Preview"},{"Win10Version":"10.0.19042.1151","Version":"19042.1151","ReleaseDate":"2021-07-29","Article":"KB5004296","Comment":"Preview"},{"Win10Version":"10.0.19043.1151","Version":"19043.1151","ReleaseDate":"2021-07-29","Article":"KB5004296","Comment":"Preview"}]}
